{"restaurant":{"name":"smart","hallList":["smart"]},"menuList":{"morning":{"1AAE13C":{"title":"게국지","course":"A","totalKcal":895,"kcal":370,"imgUrl":"https://seoseunghyun.github.io/wsharp/resource/img/pending.jpg","list":[{"title":"게국지","kcal":370},{"title":"흑미밥","kcal":329},{"title":"깻잎고기전","kcal":125},{"title":"느타리버섯볶음","kcal":56},{"title":"꼬시래기무침","kcal":15}],"hallFloor":["smart"]},"1BBE13C":{"title":"라면<br /><span style=\"font-size:12px\">(너구리)</span>","course":"B","totalKcal":898,"kcal":519,"imgUrl":"https://seoseunghyun.github.io/wsharp/resource/img/pending.jpg","list":[{"title":"라면(너구리)","kcal":519},{"title":"불고기유부초밥","kcal":267},{"title":"단무지","kcal":10},{"title":"포기김치","kcal":17},{"title":"마시는요구르트(포도)","kcal":85}],"hallFloor":["smart"]},"1EEE13C":{"title":"샌드위치 3종 中 택1","course":"T/O 샌드위치","totalKcal":952,"kcal":0,"imgUrl":"https://seoseunghyun.github.io/wsharp/resource/img/pending.jpg","list":[{"title":"샌드위치 3종 中 택1","kcal":0},{"title":"에그&크래미모닝롤","kcal":290},{"title":"모닝쌀머핀바질페스토샌드위치","kcal":300},{"title":"불고기샌드위치","kcal":250},{"title":"2종과일","kcal":112}],"hallFloor":["smart"]},"1GGE13C":{"title":"컵푸드 8종 中 택2","course":"T/O 과일","totalKcal":2045,"kcal":0,"imgUrl":"https://seoseunghyun.github.io/wsharp/resource/img/pending.jpg","list":[{"title":"컵푸드 8종 中 택2","kcal":0},{"title":"사과","kcal":237},{"title":"감귤","kcal":170},{"title":"청포도","kcal":66},{"title":"완숙계란","kcal":434},{"title":"촉촉계란&오리지널닭가슴살소시지","kcal":268},{"title":"고구마","kcal":384},{"title":"감자","kcal":211},{"title":"요거복숭아","kcal":275}],"hallFloor":["smart"]},"1HHE13C":{"title":"샐러드 2종 中 택1","course":"T/O 샐러드","totalKcal":410,"kcal":0,"imgUrl":"https://seoseunghyun.github.io/wsharp/resource/img/pending.jpg","list":[{"title":"샐러드 2종 中 택1","kcal":0},{"title":"연두부견과류샐러드","kcal":211},{"title":"카프레제샐러드","kcal":199}],"hallFloor":["smart"]},"1IIE13C":{"title":"빵 or 떡 5종 中 택1","course":"T/O 베이커리 & 떡","totalKcal":2828,"kcal":0,"imgUrl":"https://seoseunghyun.github.io/wsharp/resource/img/pending.jpg","list":[{"title":"빵 or 떡 5종 中 택1","kcal":0},{"title":"쏙쏙토스트","kcal":525},{"title":"흑당크림소보로","kcal":335},{"title":"구운치즈케이크빵","kcal":505},{"title":"다크초콜릿머핀","kcal":505},{"title":"삼색방울떡","kcal":365},{"title":"1종과일","kcal":28},{"title":"시리얼","kcal":180},{"title":"우유","kcal":180},{"title":"두유","kcal":110},{"title":"요거트","kcal":95}],"hallFloor":["smart"]},"1JJE13C":{"title":"현미고추장불고기주먹밥","course":"T/O 주먹밥","totalKcal":1129,"kcal":461,"imgUrl":"https://seoseunghyun.github.io/wsharp/resource/img/pending.jpg","list":[{"title":"현미고추장불고기주먹밥","kcal":461},{"title":"게맛살계란스크램블토핑","kcal":187},{"title":"절임반찬","kcal":18},{"title":"1종과일","kcal":120},{"title":"구운란","kcal":75},{"title":"건강즙(홍삼)","kcal":205},{"title":"오리지널닭가슴살소시지","kcal":63}],"hallFloor":["smart"]},"1WWE13C":{"title":"선식 3종 中 택1","course":"T/O 선식","totalKcal":970,"kcal":0,"imgUrl":"https://seoseunghyun.github.io/wsharp/resource/img/pending.jpg","list":[{"title":"선식 3종 中 택1","kcal":0},{"title":"단호박","kcal":176},{"title":"플레인라이트","kcal":206},{"title":"녹차","kcal":158},{"title":"우유","kcal":28},{"title":"두유","kcal":110},{"title":"삶은계란","kcal":83},{"title":"견과류","kcal":83},{"title":"2종과일","kcal":126}],"hallFloor":["smart"]},"1XXE13C":{"title":"착즙주스 4종 中 택1","course":"T/O착즙주스2","totalKcal":916,"kcal":0,"imgUrl":"https://seoseunghyun.github.io/wsharp/resource/img/pending.jpg","list":[{"title":"착즙주스 4종 中 택1","kcal":0},{"title":"밀싹애플","kcal":155},{"title":"부스트업","kcal":165},{"title":"빌베리&마리골드","kcal":165},{"title":"블랙&비타D","kcal":265},{"title":"삶은계란","kcal":83},{"title":"견과류","kcal":83}],"hallFloor":["smart"]},"1ZZE13C":{"title":"오징어튀김김밥","course":"T/O김밥/마리","totalKcal":1554,"kcal":649,"imgUrl":"https://seoseunghyun.github.io/wsharp/resource/img/pending.jpg","list":[{"title":"오징어튀김김밥","kcal":649},{"title":"½김밥+유부초밥","kcal":462},{"title":"1종과일","kcal":120},{"title":"구운란","kcal":75},{"title":"건강즙(홍삼)","kcal":205},{"title":"오리지널닭가슴살소시지","kcal":43}],"hallFloor":["smart"]}},"lunch":{"2AAE13C":{"title":"전복미역국","course":"A","totalKcal":1031,"kcal":421,"imgUrl":"https://seoseunghyun.github.io/wsharp/resource/img/pending.jpg","list":[{"title":"전복미역국","kcal":421},{"title":"흑미밥","kcal":329},{"title":"계란찜","kcal":98},{"title":"잡채어묵조림","kcal":146},{"title":"오이생채","kcal":37}],"hallFloor":["smart"]},"2BBE13C":{"title":"삼겹살고추장볶음","course":"B","totalKcal":1303,"kcal":741,"imgUrl":"https://seoseunghyun.github.io/wsharp/resource/img/pending.jpg","list":[{"title":"삼겹살고추장볶음","kcal":741},{"title":"흑미밥","kcal":312},{"title":"콩나물국","kcal":23},{"title":"연두부찜&양념장","kcal":74},{"title":"잡채어묵조림","kcal":88},{"title":"양파간장초절임","kcal":65}],"hallFloor":["smart"]},"2CCE13C":{"title":"자장면","course":"C","totalKcal":1452,"kcal":675,"imgUrl":"https://seoseunghyun.github.io/wsharp/resource/img/pending.jpg","list":[{"title":"자장면","kcal":675},{"title":"깐풍기","kcal":668},{"title":"짜사이채무침","kcal":21},{"title":"단무지","kcal":7},{"title":"황도","kcal":81}],"hallFloor":["smart"]}},"dinner":{"3AAE13C":{"title":"달래청국장찌개","course":"A","totalKcal":847,"kcal":154,"imgUrl":"https://seoseunghyun.github.io/wsharp/resource/img/pending.jpg","list":[{"title":"달래청국장찌개","kcal":154},{"title":"흑미밥","kcal":312},{"title":"고등어양념구이","kcal":329},{"title":"꽈리고추멸치볶음","kcal":46},{"title":"김구이","kcal":6}],"hallFloor":["smart"]},"3BBE13C":{"title":"잡채덮밥","course":"B","totalKcal":1163,"kcal":837,"imgUrl":"https://seoseunghyun.github.io/wsharp/resource/img/pending.jpg","list":[{"title":"잡채덮밥","kcal":837},{"title":"짬뽕국","kcal":46},{"title":"교자만두강정","kcal":215},{"title":"단무지","kcal":10},{"title":"후식(망고시미로)","kcal":55}],"hallFloor":["smart"]}},"midnight":{}}}