{"restaurant":{"name":"smart","hallList":["smart"]},"menuList":{"morning":{"1AAE13C":{"title":"꽃게묵은지찌개","course":"chef's counter A","totalKcal":897,"kcal":285,"imgUrl":"https://seoseunghyun.github.io/wsharp/resource/img/pending.jpg","list":[{"title":"꽃게묵은지찌개","kcal":285},{"title":"흑미밥","kcal":312},{"title":"햄(로스팜)계란전","kcal":219},{"title":"느타리버섯볶음","kcal":53},{"title":"상추겉절이","kcal":28}],"hallFloor":["smart"]},"1DDE13C":{"title":"★아메리칸조식★","course":"D","totalKcal":1488,"kcal":0,"imgUrl":"https://seoseunghyun.github.io/wsharp/resource/img/pending.jpg","list":[{"title":"★아메리칸조식★","kcal":0},{"title":"NEW마계토스트(마요네즈계란토스트)","kcal":218},{"title":"옥수수모닝롤","kcal":111},{"title":"양송이스프","kcal":80},{"title":"시리얼","kcal":173},{"title":"요거트","kcal":282},{"title":"비어햄구이","kcal":146},{"title":"삶은계란","kcal":44},{"title":"푸실리샐러드","kcal":185},{"title":"그린샐러드&드레싱2종","kcal":10},{"title":"샐러드토핑(체다치즈,블랙올리브)","kcal":38},{"title":"과일(바나나)","kcal":116},{"title":"주스(사과)","kcal":52},{"title":"커피","kcal":9},{"title":"우유","kcal":24}],"hallFloor":["smart"]},"1EEE13C":{"title":"샌드위치 3종 中 택1","course":"T/O 샌드위치","totalKcal":791,"kcal":0,"imgUrl":"https://seoseunghyun.github.io/wsharp/resource/img/pending.jpg","list":[{"title":"샌드위치 3종 中 택1","kcal":0},{"title":"블랙번에그샌드위치","kcal":320},{"title":"바질&참치","kcal":471}],"hallFloor":["smart"]},"1GGE13C":{"title":"컵푸드 11종 中 택2","course":"T/O 과일","totalKcal":2611,"kcal":0,"imgUrl":"https://seoseunghyun.github.io/wsharp/resource/img/pending.jpg","list":[{"title":"컵푸드 11종 中 택2","kcal":0},{"title":"사과","kcal":237},{"title":"대추방울토마토","kcal":65},{"title":"트윈핑거바나나","kcal":221},{"title":"완숙계란","kcal":434},{"title":"촉촉계란&건강즙(석류)","kcal":210},{"title":"고구마","kcal":384},{"title":"감자","kcal":211},{"title":"요거넛츠","kcal":363},{"title":"그린티쉐이크","kcal":171},{"title":"비건내추럴","kcal":149},{"title":"그레인","kcal":166}],"hallFloor":["smart"]},"1HHE13C":{"title":"일반/콤보 中 택1","course":"T/O 샐러드","totalKcal":984,"kcal":0,"imgUrl":"https://seoseunghyun.github.io/wsharp/resource/img/pending.jpg","list":[{"title":"일반/콤보 中 택1","kcal":0},{"title":"두부스틱샐러드","kcal":469},{"title":"[콤보]닭가슴살샐러드&크랜베리치킨햄샌드위치½","kcal":515}],"hallFloor":["smart"]},"1IIE13C":{"title":"빵 10종 中 택2","course":"T/O 베이커리 & 떡","totalKcal":4281,"kcal":0,"imgUrl":"https://seoseunghyun.github.io/wsharp/resource/img/pending.jpg","list":[{"title":"빵 10종 中 택2","kcal":0},{"title":"블루베리베이글","kcal":394},{"title":"고메버터식빵","kcal":484},{"title":"데리야끼치킨토스트","kcal":785},{"title":"호두단팥빵","kcal":436},{"title":"흑당크림소보로","kcal":335},{"title":"NEW미니샌드스트로베리","kcal":220},{"title":"빅초코칩머핀","kcal":640},{"title":"밀크롤인빵","kcal":520},{"title":"슈크림도넛","kcal":275},{"title":"마늘토스트","kcal":192}],"hallFloor":["smart"]},"1JJE13C":{"title":"매콤햄맛살채소주먹밥","course":"T/O 주먹밥","totalKcal":1170,"kcal":503,"imgUrl":"https://seoseunghyun.github.io/wsharp/resource/img/pending.jpg","list":[{"title":"매콤햄맛살채소주먹밥","kcal":503},{"title":"마늘종계란스크램블토핑","kcal":147},{"title":"절임반찬","kcal":6},{"title":"사과","kcal":57},{"title":"참외","kcal":25},{"title":"바나나","kcal":120},{"title":"구운란","kcal":75},{"title":"건강즙(블루베리)","kcal":39},{"title":"숯불구이맛후랑크","kcal":198}],"hallFloor":["smart"]},"1PPE13C":{"title":"호박앙금찰편","course":"T/O 떡","totalKcal":1074,"kcal":560,"imgUrl":"https://seoseunghyun.github.io/wsharp/resource/img/pending.jpg","list":[{"title":"호박앙금찰편","kcal":560},{"title":"사과","kcal":57},{"title":"참외","kcal":25},{"title":"바나나","kcal":120},{"title":"구운란","kcal":75},{"title":"건강즙(블루베리)","kcal":39},{"title":"숯불구이맛후랑크","kcal":198}],"hallFloor":["smart"]},"1SSE13C":{"title":"사과","course":"T/O 사이드","totalKcal":1652,"kcal":57,"imgUrl":"https://seoseunghyun.github.io/wsharp/resource/img/pending.jpg","list":[{"title":"사과","kcal":57},{"title":"참외","kcal":25},{"title":"바나나","kcal":120},{"title":"버섯크림컵스프","kcal":115},{"title":"구운누룽지오트밀","kcal":195},{"title":"마시는단팥죽","kcal":102},{"title":"초코첵스시리얼","kcal":117},{"title":"요플레토핑 오트&애플시나몬","kcal":83},{"title":"그릭달지않은플레인요거트","kcal":80},{"title":"어묵(크래미)치즈볼","kcal":55},{"title":"배즙숙성숯불구이맛후랑크","kcal":0},{"title":"꿀오란다바","kcal":140},{"title":"넛츠구운브라질넛","kcal":134},{"title":"퀴노아라이스크런치","kcal":130},{"title":"노니앤시트러스","kcal":32},{"title":"참고운양갱","kcal":140},{"title":"프레시넛츠파이","kcal":127}],"hallFloor":["smart"]},"1XXE13C":{"title":"착즙주스 4종 中 택1","course":"T/O착즙주스2","totalKcal":876,"kcal":0,"imgUrl":"https://seoseunghyun.github.io/wsharp/resource/img/pending.jpg","list":[{"title":"착즙주스 4종 中 택1","kcal":0},{"title":"밀싹애플","kcal":155},{"title":"헬시파인","kcal":175},{"title":"ABC주스","kcal":115},{"title":"노니&깔라만시","kcal":265},{"title":"삶은계란","kcal":83},{"title":"견과류","kcal":83}],"hallFloor":["smart"]},"1Z3E13C":{"title":"Takeout 상시코너","course":"T/O 상시코너","totalKcal":0,"kcal":0,"imgUrl":"https://seoseunghyun.github.io/wsharp/resource/img/pending.jpg","list":[{"title":"Takeout 상시코너","kcal":0}],"hallFloor":["smart"]},"1ZZE13C":{"title":"돈가스말이","course":"T/O김밥/마리","totalKcal":1359,"kcal":523,"imgUrl":"https://seoseunghyun.github.io/wsharp/resource/img/pending.jpg","list":[{"title":"돈가스말이","kcal":523},{"title":"칠리소스새우튀김","kcal":124},{"title":"피자오믈렛","kcal":37},{"title":"오이&당근","kcal":3},{"title":"고추냉이마요소스","kcal":152},{"title":"절임반찬","kcal":6},{"title":"사과","kcal":57},{"title":"참외","kcal":25},{"title":"바나나","kcal":120},{"title":"구운란","kcal":75},{"title":"건강즙(블루베리)","kcal":39},{"title":"숯불구이맛후랑크","kcal":198}],"hallFloor":["smart"]}},"lunch":{"2AAE13C":{"title":"새싹삼뚝배기불고기","course":"chef's counter A","totalKcal":903,"kcal":395,"imgUrl":"https://seoseunghyun.github.io/wsharp/resource/img/pending.jpg","list":[{"title":"새싹삼뚝배기불고기","kcal":395},{"title":"흑미밥","kcal":312},{"title":"두부조림","kcal":111},{"title":"꽈리고추멸치볶음","kcal":61},{"title":"부추생채","kcal":24}],"hallFloor":["smart"]},"2BBE13C":{"title":"NEW전복해초비빔밥","course":"chef's counter B","totalKcal":1001,"kcal":613,"imgUrl":"https://seoseunghyun.github.io/wsharp/resource/img/pending.jpg","list":[{"title":"NEW전복해초비빔밥","kcal":613},{"title":"아욱된장국","kcal":27},{"title":"완자전","kcal":211},{"title":"도토리묵&양념장","kcal":99},{"title":"고추지무침","kcal":51}],"hallFloor":["smart"]},"2CCE13C":{"title":"고기국수","course":"SnapSnack","totalKcal":901,"kcal":576,"imgUrl":"https://seoseunghyun.github.io/wsharp/resource/img/pending.jpg","list":[{"title":"고기국수","kcal":576},{"title":"NEW대파해물전","kcal":198},{"title":"배추겉절이","kcal":46},{"title":"후식(수박)","kcal":81}],"hallFloor":["smart"]},"2E2E13C":{"title":"셀프배식대","course":"셀프배식대","totalKcal":647,"kcal":0,"imgUrl":"https://seoseunghyun.github.io/wsharp/resource/img/pending.jpg","list":[{"title":"셀프배식대","kcal":0},{"title":"현미밥","kcal":300},{"title":"쌀밥","kcal":311},{"title":"김치(초숙/중숙)","kcal":20},{"title":"깍두기","kcal":16}],"hallFloor":["smart"]},"2Z2E13C":{"title":"매운시래기돼지갈비찜","course":"T/O도시락","totalKcal":1344,"kcal":635,"imgUrl":"https://seoseunghyun.github.io/wsharp/resource/img/pending.jpg","list":[{"title":"매운시래기돼지갈비찜","kcal":635},{"title":"흑미밥","kcal":312},{"title":"오이냉국","kcal":36},{"title":"동태전","kcal":155},{"title":"계란찜","kcal":110},{"title":"백김치","kcal":16},{"title":"젤리블리포도(후식)","kcal":80},{"title":"김구이","kcal":0},{"title":"삼다수","kcal":0}],"hallFloor":["smart"]},"2EEE13C":{"title":"블랙번에그샌드위치","course":"T/O 샌드위치","totalKcal":355,"kcal":320,"imgUrl":"https://seoseunghyun.github.io/wsharp/resource/img/pending.jpg","list":[{"title":"블랙번에그샌드위치","kcal":320},{"title":"건강즙(숙성흑도라지)","kcal":35}],"hallFloor":["smart"]},"2GGE13C":{"title":"컵푸드 11종 中 택2","course":"T/O 과일","totalKcal":2569,"kcal":0,"imgUrl":"https://seoseunghyun.github.io/wsharp/resource/img/pending.jpg","list":[{"title":"컵푸드 11종 中 택2","kcal":0},{"title":"사과","kcal":237},{"title":"참외","kcal":59},{"title":"NEW천도복숭아","kcal":150},{"title":"완숙계란","kcal":434},{"title":"촉촉계란&건강즙(석류)","kcal":210},{"title":"고구마","kcal":384},{"title":"감자","kcal":211},{"title":"요거넛츠","kcal":363},{"title":"그린티쉐이크","kcal":171},{"title":"비건내추럴","kcal":149},{"title":"그레인","kcal":166},{"title":"건강즙(숙성흑도라지)","kcal":35}],"hallFloor":["smart"]},"2HHE13C":{"title":"일반/베지/콤보 中 택1","course":"T/O 샐러드","totalKcal":1852,"kcal":0,"imgUrl":"https://seoseunghyun.github.io/wsharp/resource/img/pending.jpg","list":[{"title":"일반/베지/콤보 中 택1","kcal":0},{"title":"돼지목살샐러드","kcal":563},{"title":"콩불고기볶음밥","kcal":594},{"title":"&[비건토핑]견과류쌈장","kcal":55},{"title":"&[락토토핑]크림치즈","kcal":90},{"title":"[콤보]닭가슴살샐러드&크랜베리치킨햄샌드위치½","kcal":515},{"title":"건강즙(숙성흑도라지)","kcal":35}],"hallFloor":["smart"]},"2QQE13C":{"title":"빵 9종 中 택2","course":"T/O 베이커리","totalKcal":4124,"kcal":0,"imgUrl":"https://seoseunghyun.github.io/wsharp/resource/img/pending.jpg","list":[{"title":"빵 9종 中 택2","kcal":0},{"title":"블루베리베이글","kcal":394},{"title":"고메버터식빵","kcal":484},{"title":"에그타르트","kcal":785},{"title":"우유크림카스테라","kcal":436},{"title":"스위트녹차롤","kcal":335},{"title":"빅블루베리머핀","kcal":220},{"title":"플레인카스테라","kcal":640},{"title":"밀크롤인빵","kcal":520},{"title":"슈크림도넛","kcal":275},{"title":"건강즙(숙성흑도라지)","kcal":35}],"hallFloor":["smart"]},"2SSE13C":{"title":"사과","course":"T/O 사이드","totalKcal":1652,"kcal":57,"imgUrl":"https://seoseunghyun.github.io/wsharp/resource/img/pending.jpg","list":[{"title":"사과","kcal":57},{"title":"참외","kcal":25},{"title":"바나나","kcal":120},{"title":"버섯크림컵스프","kcal":115},{"title":"구운누룽지오트밀","kcal":195},{"title":"마시는단팥죽","kcal":102},{"title":"초코첵스시리얼","kcal":117},{"title":"요플레토핑 프레즐&초코청크","kcal":83},{"title":"그릭달지않은플레인요거트","kcal":80},{"title":"어묵(크래미)치즈볼","kcal":55},{"title":"숯불구이맛후랑크","kcal":0},{"title":"꿀오란다바","kcal":140},{"title":"넛츠구운브라질넛","kcal":134},{"title":"퀴노아라이스크런치","kcal":130},{"title":"노니앤시트러스","kcal":32},{"title":"참고운양갱","kcal":140},{"title":"프레시넛츠파이","kcal":127}],"hallFloor":["smart"]},"2YYE13C":{"title":"착즙주스 4종 中 택1","course":"T/O착즙주스","totalKcal":981,"kcal":0,"imgUrl":"https://seoseunghyun.github.io/wsharp/resource/img/pending.jpg","list":[{"title":"착즙주스 4종 中 택1","kcal":0},{"title":"유자바나나","kcal":225},{"title":"헬시파인","kcal":175},{"title":"ABC주스","kcal":115},{"title":"블랙&비타D","kcal":265},{"title":"삶은계란","kcal":83},{"title":"견과류","kcal":83},{"title":"건강즙(숙성흑도라지)","kcal":35}],"hallFloor":["smart"]},"2Z1E13C":{"title":"새우튀김말이","course":"T/O김밥/마리","totalKcal":1582,"kcal":555,"imgUrl":"https://seoseunghyun.github.io/wsharp/resource/img/pending.jpg","list":[{"title":"새우튀김말이","kcal":555},{"title":"미니핫도그","kcal":174},{"title":"계란구이","kcal":38},{"title":"과카몰리토핑","kcal":47},{"title":"갈릭디핑소스","kcal":184},{"title":"절임반찬","kcal":38},{"title":"사과","kcal":57},{"title":"참외","kcal":25},{"title":"바나나","kcal":120},{"title":"구운란","kcal":75},{"title":"요거트(딸기)","kcal":92},{"title":"숯불구이맛후랑크","kcal":142},{"title":"건강즙(숙성흑도라지)","kcal":35}],"hallFloor":["smart"]},"2Z3E13C":{"title":"Takeout 상시코너","course":"T/O 상시코너","totalKcal":0,"kcal":0,"imgUrl":"https://seoseunghyun.github.io/wsharp/resource/img/pending.jpg","list":[{"title":"Takeout 상시코너","kcal":0}],"hallFloor":["smart"]},"2MME13C":{"title":"꽁치김치조림","course":"추가찬","totalKcal":204,"kcal":204,"imgUrl":"https://seoseunghyun.github.io/wsharp/resource/img/pending.jpg","list":[{"title":"꽁치김치조림","kcal":204}],"hallFloor":["smart"]}},"dinner":{"3AAE13C":{"title":"콩나물해장국","course":"chef's counter A","totalKcal":891,"kcal":376,"imgUrl":"https://seoseunghyun.github.io/wsharp/resource/img/pending.jpg","list":[{"title":"콩나물해장국","kcal":376},{"title":"계란공기(수란)","kcal":37},{"title":"쌀밥","kcal":314},{"title":"명태초무침","kcal":63},{"title":"마늘종건새우볶음","kcal":54},{"title":"깻잎지무침","kcal":47}],"hallFloor":["smart"]},"3CCE13C":{"title":"라면<br /><span style=\"font-size:12px\">(해물맛안성탕면)</span>","course":"SnapSnack","totalKcal":895,"kcal":565,"imgUrl":"https://seoseunghyun.github.io/wsharp/resource/img/pending.jpg","list":[{"title":"라면(해물맛안성탕면)","kcal":565},{"title":"불고기유부초밥","kcal":283},{"title":"단무지","kcal":10},{"title":"포기김치","kcal":17},{"title":"후식(떠먹는요구르트)","kcal":20}],"hallFloor":["smart"]},"3EEE13C":{"title":"샌드위치 2종 中 택1","course":"T/O 샌드위치","totalKcal":1052,"kcal":0,"imgUrl":"https://seoseunghyun.github.io/wsharp/resource/img/pending.jpg","list":[{"title":"샌드위치 2종 中 택1","kcal":0},{"title":"단호박&로제치킨밸런스샌드위치","kcal":500},{"title":"후레쉬에그햄샌드위치","kcal":552}],"hallFloor":["smart"]},"3FFE13C":{"title":"불낙죽","course":"T/O 죽","totalKcal":866,"kcal":818,"imgUrl":"https://seoseunghyun.github.io/wsharp/resource/img/pending.jpg","list":[{"title":"불낙죽","kcal":818},{"title":"쇠고기장조림","kcal":39},{"title":"오징어젓갈무침","kcal":9}],"hallFloor":["smart"]},"3GGE13C":{"title":"컵푸드 10종 中 택2","course":"T/O 과일","totalKcal":2140,"kcal":0,"imgUrl":"https://seoseunghyun.github.io/wsharp/resource/img/pending.jpg","list":[{"title":"컵푸드 10종 中 택2","kcal":0},{"title":"참외","kcal":59},{"title":"트윈핑거바나나","kcal":127},{"title":"사과","kcal":32},{"title":"완숙계란","kcal":434},{"title":"촉촉계란&건강즙(석류)","kcal":210},{"title":"고구마","kcal":384},{"title":"감자","kcal":211},{"title":"요거넛츠","kcal":363},{"title":"그린티쉐이크","kcal":171},{"title":"비건내추럴","kcal":149}],"hallFloor":["smart"]},"3HHE13C":{"title":"일반/베지/콤보 中 택1","course":"T/O 샐러드","totalKcal":468,"kcal":0,"imgUrl":"https://seoseunghyun.github.io/wsharp/resource/img/pending.jpg","list":[{"title":"일반/베지/콤보 中 택1","kcal":0},{"title":"S라인샐러드","kcal":468}],"hallFloor":["smart"]},"3RRE13C":{"title":"빵 5종 中 택2","course":"T/O 베이커리","totalKcal":2171,"kcal":0,"imgUrl":"https://seoseunghyun.github.io/wsharp/resource/img/pending.jpg","list":[{"title":"빵 5종 中 택2","kcal":0},{"title":"고메버터식빵","kcal":484},{"title":"스위트녹차롤","kcal":335},{"title":"빅초코칩머핀","kcal":640},{"title":"에그타르트","kcal":520},{"title":"다쿠아즈","kcal":192}],"hallFloor":["smart"]},"3SSE13C":{"title":"사과","course":"T/O 사이드","totalKcal":1652,"kcal":57,"imgUrl":"https://seoseunghyun.github.io/wsharp/resource/img/pending.jpg","list":[{"title":"사과","kcal":57},{"title":"참외","kcal":25},{"title":"바나나","kcal":120},{"title":"버섯크림컵스프","kcal":115},{"title":"구운누룽지오트밀","kcal":195},{"title":"마시는단팥죽","kcal":102},{"title":"초코첵스시리얼","kcal":117},{"title":"요플레토핑 프레즐&초코청크","kcal":83},{"title":"그릭달지않은플레인요거트","kcal":80},{"title":"어묵(크래미)치즈볼","kcal":55},{"title":"숯불구이맛후랑크","kcal":0},{"title":"꿀오란다바","kcal":140},{"title":"넛츠구운브라질넛","kcal":134},{"title":"퀴노아라이스크런치","kcal":130},{"title":"노니앤시트러스","kcal":32},{"title":"참고운양갱","kcal":140},{"title":"프레시넛츠파이","kcal":127}],"hallFloor":["smart"]},"3WWE13C":{"title":"Takeout 상시코너","course":"T/O 상시코너","totalKcal":0,"kcal":0,"imgUrl":"https://seoseunghyun.github.io/wsharp/resource/img/pending.jpg","list":[{"title":"Takeout 상시코너","kcal":0}],"hallFloor":["smart"]},"3YYE13C":{"title":"착즙주스 4종 中 택1","course":"T/O착즙주스","totalKcal":946,"kcal":0,"imgUrl":"https://seoseunghyun.github.io/wsharp/resource/img/pending.jpg","list":[{"title":"착즙주스 4종 中 택1","kcal":0},{"title":"유자바나나","kcal":225},{"title":"헬시파인","kcal":175},{"title":"ABC주스","kcal":115},{"title":"블랙&비타D","kcal":265},{"title":"삶은계란","kcal":83},{"title":"견과류","kcal":83}],"hallFloor":["smart"]}},"midnight":{}}}