{"restaurant":{"name":"r3","hallList":["b1","3"]},"menuList":{"morning":{"1AAE5BA":{"title":"쇠고기떡국","course":"탕맛기픈","totalKcal":1039,"kcal":421,"imgUrl":"https://seoseunghyun.github.io/wsharp/resource/img/pending.jpg","list":[{"title":"쇠고기떡국","kcal":421},{"title":"흑미밥","kcal":312},{"title":"가지두루치기","kcal":86},{"title":"진미채간장볶음","kcal":102},{"title":"브로콜리숙회&초장","kcal":118}],"hallFloor":["3"]},"1BBE5BA":{"title":"조기구이","course":"탕맛기픈","totalKcal":793,"kcal":140,"imgUrl":"https://seoseunghyun.github.io/wsharp/resource/img/pending.jpg","list":[{"title":"조기구이","kcal":140},{"title":"흑미밥","kcal":312},{"title":"얼갈이된장국","kcal":35},{"title":"가지두루치기","kcal":86},{"title":"진미채간장볶음","kcal":102},{"title":"브로콜리숙회&초장","kcal":118}],"hallFloor":["3"]},"1DDE5BA":{"title":"콩나물라면","course":"SnapSnack","totalKcal":1140,"kcal":557,"imgUrl":"https://seoseunghyun.github.io/wsharp/resource/img/pending.jpg","list":[{"title":"콩나물라면","kcal":557},{"title":"충무김밥(오징어&어묵)","kcal":445},{"title":"단무지","kcal":7},{"title":"1종과일","kcal":131}],"hallFloor":[]},"1AAE5B9":{"title":"★아메리칸조식★","course":"BROWN GRILL","totalKcal":1577,"kcal":0,"imgUrl":"https://seoseunghyun.github.io/wsharp/resource/img/pending.jpg","list":[{"title":"★아메리칸조식★","kcal":0},{"title":"옛날토스트","kcal":528},{"title":"식물성모닝롤","kcal":70},{"title":"크림스프","kcal":177},{"title":"시리얼","kcal":46},{"title":"토핑요거트","kcal":93},{"title":"화이트소시지구이","kcal":264},{"title":"감자튀김","kcal":176},{"title":"그린샐러드","kcal":9},{"title":"코올슬로","kcal":146},{"title":"1종과일","kcal":16},{"title":"음료","kcal":52}],"hallFloor":[]},"1HHE5B9":{"title":"콩나물라면","course":"XingFu(China)","totalKcal":1140,"kcal":557,"imgUrl":"https://seoseunghyun.github.io/wsharp/resource/img/pending.jpg","list":[{"title":"콩나물라면","kcal":557},{"title":"충무김밥(오징어&어묵)","kcal":445},{"title":"단무지","kcal":7},{"title":"1종과일","kcal":131}],"hallFloor":["3"]},"1AAE5B8":{"title":"★아메리칸조식★","course":"가츠&엔","totalKcal":1577,"kcal":0,"imgUrl":"https://seoseunghyun.github.io/wsharp/resource/img/pending.jpg","list":[{"title":"★아메리칸조식★","kcal":0},{"title":"옛날토스트","kcal":528},{"title":"식물성모닝롤","kcal":70},{"title":"크림스프","kcal":177},{"title":"시리얼","kcal":46},{"title":"토핑요거트","kcal":93},{"title":"화이트소시지구이","kcal":264},{"title":"감자튀김","kcal":176},{"title":"그린샐러드","kcal":9},{"title":"코올슬로","kcal":146},{"title":"1종과일","kcal":16},{"title":"음료","kcal":52}],"hallFloor":["3"]},"1GGE5B8":{"title":"현미고추장불고기주먹밥","course":"T/O 주먹밥","totalKcal":1387,"kcal":501,"imgUrl":"https://seoseunghyun.github.io/wsharp/resource/img/pending.jpg","list":[{"title":"현미고추장불고기주먹밥","kcal":501},{"title":"게맛살 계란스크램블토핑","kcal":172},{"title":"절임반찬","kcal":7},{"title":"사과","kcal":237},{"title":"방울토마토","kcal":32},{"title":"바나나","kcal":221},{"title":"삶은계란","kcal":73},{"title":"건강즙(블루베리)","kcal":50},{"title":"요거트","kcal":94}],"hallFloor":[]},"1HHE5B8":{"title":"계란지단말이","course":"T/O 말이","totalKcal":1526,"kcal":527,"imgUrl":"https://seoseunghyun.github.io/wsharp/resource/img/pending.jpg","list":[{"title":"계란지단말이","kcal":527},{"title":"닭강정","kcal":165},{"title":"새송이버섯구이","kcal":9},{"title":"오이&당근","kcal":7},{"title":"명란마요소스","kcal":104},{"title":"절임반찬","kcal":7},{"title":"사과","kcal":237},{"title":"방울토마토","kcal":32},{"title":"바나나","kcal":221},{"title":"삶은계란","kcal":73},{"title":"건강즙(블루베리)","kcal":50},{"title":"요거트","kcal":94}],"hallFloor":[]},"1AAE5B7":{"title":"튜나클럽","course":"T/O 샌드위치","totalKcal":1380,"kcal":445,"imgUrl":"https://seoseunghyun.github.io/wsharp/resource/img/pending.jpg","list":[{"title":"튜나클럽","kcal":445},{"title":"NEW아몬드크림치즈베이글","kcal":540},{"title":"에그&맥적구이모닝롤","kcal":395}],"hallFloor":["3"]},"1BBE5B7":{"title":"사과","course":"T/O 과일","totalKcal":2949,"kcal":237,"imgUrl":"https://seoseunghyun.github.io/wsharp/resource/img/pending.jpg","list":[{"title":"사과","kcal":237},{"title":"파인애플","kcal":127},{"title":"캠벨포도","kcal":383},{"title":"완숙계란","kcal":434},{"title":"완숙계란&뉴트리션바(카카오닙스)","kcal":355},{"title":"고구마","kcal":384},{"title":"감자","kcal":211},{"title":"요거초코통통","kcal":344},{"title":"귀리쉐이크","kcal":172},{"title":"비건그린","kcal":141},{"title":"초코","kcal":161}],"hallFloor":["3"]},"1CCE5B7":{"title":"베이컨에그샐러드","course":"T/O 샐러드","totalKcal":2262,"kcal":600,"imgUrl":"https://seoseunghyun.github.io/wsharp/resource/img/pending.jpg","list":[{"title":"베이컨에그샐러드","kcal":600},{"title":"머슬랭팩(고구마밥)","kcal":572},{"title":"템페구이와 콩소스","kcal":407},{"title":"&[비건토핑]견과류","kcal":90},{"title":"&[오보토핑]메추리알","kcal":50},{"title":"[콤보]½베이컨에그샐러드+½시그니쳐디럭스샌드위치","kcal":543}],"hallFloor":["3"]},"1DDE5B7":{"title":"건강한베리베리브레드","course":"T/O 빵","totalKcal":3717,"kcal":280,"imgUrl":"https://seoseunghyun.github.io/wsharp/resource/img/pending.jpg","list":[{"title":"건강한베리베리브레드","kcal":280},{"title":"카스테라","kcal":388},{"title":"피자바게트","kcal":475},{"title":"월넛크림치즈스틱","kcal":310},{"title":"슈크림소보로","kcal":435},{"title":"완두앙금빵","kcal":250},{"title":"시나몬롤페스츄리빵","kcal":330},{"title":"NEW꿀떡꿀떡","kcal":299},{"title":"빅초코칩머핀","kcal":640},{"title":"포켓샌드땅콩크림빵","kcal":310}],"hallFloor":["3"]},"1EEE5B7":{"title":"현미고추장불고기주먹밥","course":"T/O 주먹밥","totalKcal":1387,"kcal":501,"imgUrl":"https://seoseunghyun.github.io/wsharp/resource/img/pending.jpg","list":[{"title":"현미고추장불고기주먹밥","kcal":501},{"title":"게맛살 계란스크램블토핑","kcal":172},{"title":"절임반찬","kcal":7},{"title":"사과","kcal":237},{"title":"방울토마토","kcal":32},{"title":"바나나","kcal":221},{"title":"삶은계란","kcal":73},{"title":"건강즙(블루베리)","kcal":50},{"title":"요거트","kcal":94}],"hallFloor":["3"]},"1FFE5B7":{"title":"한라봉증편","course":"T/O 떡","totalKcal":934,"kcal":227,"imgUrl":"https://seoseunghyun.github.io/wsharp/resource/img/pending.jpg","list":[{"title":"한라봉증편","kcal":227},{"title":"사과","kcal":237},{"title":"방울토마토","kcal":32},{"title":"바나나","kcal":221},{"title":"삶은계란","kcal":73},{"title":"건강즙(블루베리)","kcal":50},{"title":"요거트","kcal":94}],"hallFloor":["3"]},"1HHE5B7":{"title":"계란지단말이","course":"T/O 말이","totalKcal":1526,"kcal":527,"imgUrl":"https://seoseunghyun.github.io/wsharp/resource/img/pending.jpg","list":[{"title":"계란지단말이","kcal":527},{"title":"닭강정","kcal":165},{"title":"새송이버섯구이","kcal":9},{"title":"오이&당근","kcal":7},{"title":"명란마요소스","kcal":104},{"title":"절임반찬","kcal":7},{"title":"사과","kcal":237},{"title":"방울토마토","kcal":32},{"title":"바나나","kcal":221},{"title":"삶은계란","kcal":73},{"title":"건강즙(블루베리)","kcal":50},{"title":"요거트","kcal":94}],"hallFloor":["3"]},"1IIE5B7":{"title":"사과","course":"T/O 빵,샌드위치 17종사이드","totalKcal":2330,"kcal":237,"imgUrl":"https://seoseunghyun.github.io/wsharp/resource/img/pending.jpg","list":[{"title":"사과","kcal":237},{"title":"대추방울토마토","kcal":32},{"title":"바나나","kcal":221},{"title":"콘크림컵스프","kcal":95},{"title":"아몬드푸레이크시리얼","kcal":128},{"title":"마시는고구마죽","kcal":110},{"title":"그릭달지않은요거트","kcal":80},{"title":"요거톡(초코그래놀라)","kcal":169},{"title":"허쉬화이트칩위드아몬드쿠키","kcal":247},{"title":"휠터치소시지","kcal":189},{"title":"첵스초코펀오리지날바","kcal":107},{"title":"넛츠피아나인믹스그릭","kcal":47},{"title":"퀴노아넛츠크런치","kcal":133},{"title":"연양갱","kcal":160},{"title":"발효오디와배","kcal":25},{"title":"쁘띠첼(밀감)","kcal":65},{"title":"카라멜팝콘","kcal":285}],"hallFloor":["3"]},"1KFE5B7":{"title":"광명찾은결명자차","course":"T/O 선택음료","totalKcal":5150,"kcal":0,"imgUrl":"https://seoseunghyun.github.io/wsharp/resource/img/pending.jpg","list":[{"title":"광명찾은결명자차","kcal":0},{"title":"닥터유드링크,초코","kcal":167},{"title":"덴마크드링킹,딸기","kcal":260},{"title":"덴마크드링킹,청포도","kcal":280},{"title":"디카페인아메리카노","kcal":16},{"title":"딸기우유","kcal":230},{"title":"레드스무디페트","kcal":180},{"title":"르블렌자몽히비스커스","kcal":36},{"title":"마시는요구르트,액티비아","kcal":82},{"title":"마시는요구르트,윌","kcal":115},{"title":"멸균흰우유","kcal":125},{"title":"모닝시리얼우유","kcal":185},{"title":"바나나우유","kcal":208},{"title":"백산수","kcal":0},{"title":"베지밀B두유","kcal":120},{"title":"비타민워터,파워씨(용과)","kcal":92},{"title":"산펠레그리노,리모네타","kcal":117},{"title":"산펠레그리노,아란시아타로싸","kcal":132},{"title":"산펠레그리노,폼펠모","kcal":137},{"title":"삼다수","kcal":0},{"title":"소화가잘되는우유","kcal":105},{"title":"씨그램,라임","kcal":0},{"title":"아몬드브리즈,언스위트","kcal":35},{"title":"아몬드브리즈,오리지널","kcal":45},{"title":"아몬드브리즈,프로틴","kcal":65},{"title":"아이시스에코","kcal":0},{"title":"아임보리","kcal":0},{"title":"아침햇살미유","kcal":70},{"title":"알로에베라킹페트","kcal":185},{"title":"야채랑사과","kcal":95},{"title":"약콩두유","kcal":75},{"title":"에비앙","kcal":0},{"title":"옥수수수염차","kcal":0},{"title":"요구르트,그란데","kcal":140},{"title":"이프청포도주스","kcal":150},{"title":"저지방우유","kcal":80},{"title":"칠성사이다","kcal":110},{"title":"코카콜라","kcal":108},{"title":"코카콜라제로","kcal":0},{"title":"코코아우유","kcal":250},{"title":"콜드,오렌지주스","kcal":135},{"title":"콜드,포도주스","kcal":152},{"title":"콜드브루아메리카노","kcal":10},{"title":"토레타캔","kcal":58},{"title":"트레비,레몬","kcal":0},{"title":"트레비,플레인","kcal":0},{"title":"티오피,마스터라떼","kcal":110},{"title":"티즐유자그린티페트","kcal":200},{"title":"파워에이드캔","kcal":36},{"title":"페리에,라임","kcal":0},{"title":"페리에,피치","kcal":0},{"title":"헛개수","kcal":0},{"title":"현미참두유 ","kcal":144},{"title":"흰우유,200ML","kcal":130},{"title":"흰우유,250ML","kcal":180}],"hallFloor":["3"]},"1KGE5B7":{"title":"T/O 상시코너","course":"T/O 상시코너","totalKcal":0,"kcal":0,"imgUrl":"https://seoseunghyun.github.io/wsharp/resource/img/pending.jpg","list":[{"title":"T/O 상시코너","kcal":0}],"hallFloor":["3"]},"1KKE5B7":{"title":"그린데이","course":"T/O 착즙주스1","totalKcal":696,"kcal":155,"imgUrl":"https://seoseunghyun.github.io/wsharp/resource/img/pending.jpg","list":[{"title":"그린데이","kcal":155},{"title":"썬라이즈","kcal":170},{"title":"프레시토마토","kcal":110},{"title":"ABC주스","kcal":115},{"title":"삶은계란","kcal":73},{"title":"견과류","kcal":73}],"hallFloor":["3"]}},"lunch":{"2AAE5BA":{"title":"돼지고기김치찌개","course":"탕맛기픈","totalKcal":912,"kcal":317,"imgUrl":"https://seoseunghyun.github.io/wsharp/resource/img/pending.jpg","list":[{"title":"돼지고기김치찌개","kcal":317},{"title":"흑미밥","kcal":312},{"title":"메추리알장조림","kcal":143},{"title":"감자채햄볶음","kcal":108},{"title":"오이생채","kcal":32}],"hallFloor":["3"]},"2BBE5BA":{"title":"돼지고기콩나물두루치기","course":"봄이온소반","totalKcal":974,"kcal":341,"imgUrl":"https://seoseunghyun.github.io/wsharp/resource/img/pending.jpg","list":[{"title":"돼지고기콩나물두루치기","kcal":341},{"title":"흑미밥","kcal":312},{"title":"무들깻국","kcal":38},{"title":"메추리알장조림","kcal":143},{"title":"감자채햄볶음","kcal":108},{"title":"오이생채","kcal":32}],"hallFloor":[]},"2CCE5BA":{"title":"황태순두부찌개","course":"탕맛기픈","totalKcal":840,"kcal":245,"imgUrl":"https://seoseunghyun.github.io/wsharp/resource/img/pending.jpg","list":[{"title":"황태순두부찌개","kcal":245},{"title":"흑미밥","kcal":312},{"title":"메추리알장조림","kcal":143},{"title":"감자채햄볶음","kcal":108},{"title":"오이생채","kcal":32}],"hallFloor":["3"]},"2DDE5BA":{"title":"새우완탕칼국수","course":"SnapSnack","totalKcal":756,"kcal":480,"imgUrl":"https://seoseunghyun.github.io/wsharp/resource/img/pending.jpg","list":[{"title":"새우완탕칼국수","kcal":480},{"title":"부추전","kcal":205},{"title":"배추겉절이","kcal":26},{"title":"푸딩","kcal":45}],"hallFloor":[]},"2GGE5BA":{"title":"셀프배식대","course":"셀프배식대","totalKcal":675,"kcal":0,"imgUrl":"https://seoseunghyun.github.io/wsharp/resource/img/pending.jpg","list":[{"title":"셀프배식대","kcal":0},{"title":"현미밥","kcal":300},{"title":"쌀밥","kcal":313},{"title":"깍두기","kcal":38},{"title":"포기김치(저염)","kcal":24}],"hallFloor":["3"]},"2BBE5B9":{"title":"양송이비프카레라이스","course":"BROWN GRILL","totalKcal":950,"kcal":693,"imgUrl":"https://seoseunghyun.github.io/wsharp/resource/img/pending.jpg","list":[{"title":"양송이비프카레라이스","kcal":693},{"title":"새우가스","kcal":97},{"title":"타르타르소스","kcal":56},{"title":"팽이버섯장국","kcal":44},{"title":"그린샐러드","kcal":20},{"title":"무비트피클","kcal":40}],"hallFloor":[]},"2DDE5B9":{"title":"양송이비프카레라이스","course":"가츠&엔","totalKcal":950,"kcal":693,"imgUrl":"https://seoseunghyun.github.io/wsharp/resource/img/pending.jpg","list":[{"title":"양송이비프카레라이스","kcal":693},{"title":"새우가스","kcal":97},{"title":"타르타르소스","kcal":56},{"title":"팽이버섯장국","kcal":44},{"title":"그린샐러드","kcal":20},{"title":"무비트피클","kcal":40}],"hallFloor":["3"]},"2EEE5B9":{"title":"돌솥제육덮밥","course":"가츠&엔","totalKcal":898,"kcal":641,"imgUrl":"https://seoseunghyun.github.io/wsharp/resource/img/pending.jpg","list":[{"title":"돌솥제육덮밥","kcal":641},{"title":"새우가스","kcal":97},{"title":"타르타르소스","kcal":56},{"title":"팽이버섯장국","kcal":44},{"title":"그린샐러드","kcal":20},{"title":"무비트피클","kcal":40}],"hallFloor":["3"]},"2FFE5B9":{"title":"새우완탕칼국수","course":"XingFu(China)","totalKcal":740,"kcal":480,"imgUrl":"https://seoseunghyun.github.io/wsharp/resource/img/pending.jpg","list":[{"title":"새우완탕칼국수","kcal":480},{"title":"감자전","kcal":181},{"title":"배추겉절이","kcal":26},{"title":"망고푸딩","kcal":53}],"hallFloor":["3"]},"2EEE5B8":{"title":"햄<br /><span style=\"font-size:12px\">(스팸)</span>계란볶음밥도시락","course":"우리味각면","totalKcal":1265,"kcal":646,"imgUrl":"https://seoseunghyun.github.io/wsharp/resource/img/pending.jpg","list":[{"title":"햄(스팸)계란볶음밥도시락","kcal":646},{"title":"&계란후라이","kcal":78},{"title":"팽이버섯장국","kcal":44},{"title":"왕새우만두튀김","kcal":152},{"title":"두부땅콩강정","kcal":160},{"title":"고구마샐러드","kcal":116},{"title":"볶음김치","kcal":69},{"title":"김구이","kcal":0},{"title":"생수","kcal":0}],"hallFloor":[]},"2HHE5B8":{"title":"돈가스말이","course":"T/O 말이","totalKcal":1583,"kcal":650,"imgUrl":"https://seoseunghyun.github.io/wsharp/resource/img/pending.jpg","list":[{"title":"돈가스말이","kcal":650},{"title":"계란말이","kcal":80},{"title":"소시지구이","kcal":61},{"title":"방울토마토","kcal":16},{"title":"고추장멸치토핑","kcal":37},{"title":"살사소스","kcal":9},{"title":"절임반찬","kcal":37},{"title":"사과","kcal":237},{"title":"방울토마토","kcal":32},{"title":"바나나","kcal":221},{"title":"삶은계란","kcal":73},{"title":"건강즙(석류)","kcal":50},{"title":"핫바","kcal":80}],"hallFloor":[]},"2TTE5B7":{"title":"햄<br /><span style=\"font-size:12px\">(스팸)</span>계란볶음밥도시락","course":"&lt;Take Me Out&gt;","totalKcal":1265,"kcal":646,"imgUrl":"https://seoseunghyun.github.io/wsharp/resource/img/pending.jpg","list":[{"title":"햄(스팸)계란볶음밥도시락","kcal":646},{"title":"&계란후라이","kcal":78},{"title":"팽이버섯장국","kcal":44},{"title":"왕새우만두튀김","kcal":152},{"title":"두부땅콩강정","kcal":160},{"title":"고구마샐러드","kcal":116},{"title":"볶음김치","kcal":69},{"title":"김구이","kcal":0},{"title":"생수","kcal":0}],"hallFloor":["3"]},"2AAE5B7":{"title":"튜나클럽","course":"T/O 샌드위치","totalKcal":445,"kcal":445,"imgUrl":"https://seoseunghyun.github.io/wsharp/resource/img/pending.jpg","list":[{"title":"튜나클럽","kcal":445}],"hallFloor":["3"]},"2BBE5B7":{"title":"허니듀메론","course":"T/O 과일","totalKcal":2577,"kcal":65,"imgUrl":"https://seoseunghyun.github.io/wsharp/resource/img/pending.jpg","list":[{"title":"허니듀메론","kcal":65},{"title":"그린키위","kcal":62},{"title":"캠벨포도","kcal":383},{"title":"완숙계란","kcal":434},{"title":"완숙계란&닭가슴살육포(매콤)","kcal":220},{"title":"고구마","kcal":384},{"title":"감자","kcal":211},{"title":"요거초코통통","kcal":344},{"title":"귀리쉐이크","kcal":172},{"title":"비건그린","kcal":141},{"title":"초코","kcal":161}],"hallFloor":["3"]},"2CCE5B7":{"title":"돼지목살샐러드","course":"T/O 샐러드","totalKcal":2066,"kcal":563,"imgUrl":"https://seoseunghyun.github.io/wsharp/resource/img/pending.jpg","list":[{"title":"돼지목살샐러드","kcal":563},{"title":"식스펙샐러드","kcal":495},{"title":"콩불고기화이타","kcal":377},{"title":"&[비건토핑]살사소스","kcal":14},{"title":"&[락토소스]샤워크림","kcal":74},{"title":"[콤보]½베이컨에그샐러드+½시그니쳐디럭스샌드위치","kcal":543}],"hallFloor":["3"]},"2DDE5B7":{"title":"건강한베리베리브레드","course":"T/O 빵","totalKcal":3717,"kcal":280,"imgUrl":"https://seoseunghyun.github.io/wsharp/resource/img/pending.jpg","list":[{"title":"건강한베리베리브레드","kcal":280},{"title":"카스테라","kcal":388},{"title":"피자바게트","kcal":475},{"title":"월넛크림치즈스틱","kcal":310},{"title":"슈크림소보로","kcal":435},{"title":"완두앙금빵","kcal":250},{"title":"시나몬롤페스츄리빵","kcal":330},{"title":"NEW꿀떡꿀떡","kcal":299},{"title":"빅초코칩머핀","kcal":640},{"title":"포켓샌드땅콩크림빵","kcal":310}],"hallFloor":["3"]},"2IIE5B7":{"title":"사과","course":"T/O 빵,샌드위치 17종사이드","totalKcal":2330,"kcal":237,"imgUrl":"https://seoseunghyun.github.io/wsharp/resource/img/pending.jpg","list":[{"title":"사과","kcal":237},{"title":"대추방울토마토","kcal":32},{"title":"바나나","kcal":221},{"title":"콘크림컵스프","kcal":95},{"title":"아몬드푸레이크시리얼","kcal":128},{"title":"마시는고구마죽","kcal":110},{"title":"그릭달지않은요거트","kcal":80},{"title":"요거톡(초코그래놀라)","kcal":169},{"title":"허쉬화이트칩위드아몬드쿠키","kcal":247},{"title":"휠터치소시지","kcal":189},{"title":"첵스초코펀오리지날바","kcal":107},{"title":"넛츠피아나인믹스그릭","kcal":47},{"title":"퀴노아넛츠크런치","kcal":133},{"title":"연양갱","kcal":160},{"title":"발효오디와배","kcal":25},{"title":"쁘띠첼(밀감)","kcal":65},{"title":"카라멜팝콘","kcal":285}],"hallFloor":["3"]},"2KFE5B7":{"title":"광명찾은결명자차","course":"T/O 선택음료","totalKcal":5150,"kcal":0,"imgUrl":"https://seoseunghyun.github.io/wsharp/resource/img/pending.jpg","list":[{"title":"광명찾은결명자차","kcal":0},{"title":"닥터유드링크,초코","kcal":167},{"title":"덴마크드링킹,딸기","kcal":260},{"title":"덴마크드링킹,청포도","kcal":280},{"title":"디카페인아메리카노","kcal":16},{"title":"딸기우유","kcal":230},{"title":"레드스무디페트","kcal":180},{"title":"르블렌자몽히비스커스","kcal":36},{"title":"마시는요구르트,액티비아","kcal":82},{"title":"마시는요구르트,윌","kcal":115},{"title":"멸균흰우유","kcal":125},{"title":"모닝시리얼우유","kcal":185},{"title":"바나나우유","kcal":208},{"title":"백산수","kcal":0},{"title":"베지밀B두유","kcal":120},{"title":"비타민워터,파워씨(용과)","kcal":92},{"title":"산펠레그리노,리모네타","kcal":117},{"title":"산펠레그리노,아란시아타로싸","kcal":132},{"title":"산펠레그리노,폼펠모","kcal":137},{"title":"삼다수","kcal":0},{"title":"소화가잘되는우유","kcal":105},{"title":"씨그램,라임","kcal":0},{"title":"아몬드브리즈,언스위트","kcal":35},{"title":"아몬드브리즈,오리지널","kcal":45},{"title":"아몬드브리즈,프로틴","kcal":65},{"title":"아이시스에코","kcal":0},{"title":"아임보리","kcal":0},{"title":"아침햇살미유","kcal":70},{"title":"알로에베라킹페트","kcal":185},{"title":"야채랑사과","kcal":95},{"title":"약콩두유","kcal":75},{"title":"에비앙","kcal":0},{"title":"옥수수수염차","kcal":0},{"title":"요구르트,그란데","kcal":140},{"title":"이프청포도주스","kcal":150},{"title":"저지방우유","kcal":80},{"title":"칠성사이다","kcal":110},{"title":"코카콜라","kcal":108},{"title":"코카콜라제로","kcal":0},{"title":"코코아우유","kcal":250},{"title":"콜드,오렌지주스","kcal":135},{"title":"콜드,포도주스","kcal":152},{"title":"콜드브루아메리카노","kcal":10},{"title":"토레타캔","kcal":58},{"title":"트레비,레몬","kcal":0},{"title":"트레비,플레인","kcal":0},{"title":"티오피,마스터라떼","kcal":110},{"title":"티즐유자그린티페트","kcal":200},{"title":"파워에이드캔","kcal":36},{"title":"페리에,라임","kcal":0},{"title":"페리에,피치","kcal":0},{"title":"헛개수","kcal":0},{"title":"현미참두유 ","kcal":144},{"title":"흰우유,200ML","kcal":130},{"title":"흰우유,250ML","kcal":180}],"hallFloor":["3"]},"2KGE5B7":{"title":"T/O 상시코너","course":"T/O 상시코너","totalKcal":0,"kcal":0,"imgUrl":"https://seoseunghyun.github.io/wsharp/resource/img/pending.jpg","list":[{"title":"T/O 상시코너","kcal":0}],"hallFloor":["3"]},"2KKE5B7":{"title":"그린데이","course":"T/O 착즙주스1","totalKcal":696,"kcal":155,"imgUrl":"https://seoseunghyun.github.io/wsharp/resource/img/pending.jpg","list":[{"title":"그린데이","kcal":155},{"title":"썬라이즈","kcal":170},{"title":"프레시토마토","kcal":110},{"title":"ABC주스","kcal":115},{"title":"삶은계란","kcal":73},{"title":"견과류","kcal":73}],"hallFloor":["3"]},"2LLE5B7":{"title":"돈가스말이","course":"T/O 말이","totalKcal":1583,"kcal":650,"imgUrl":"https://seoseunghyun.github.io/wsharp/resource/img/pending.jpg","list":[{"title":"돈가스말이","kcal":650},{"title":"계란말이","kcal":80},{"title":"소시지구이","kcal":61},{"title":"방울토마토","kcal":16},{"title":"고추장멸치토핑","kcal":37},{"title":"살사소스","kcal":9},{"title":"절임반찬","kcal":37},{"title":"사과","kcal":237},{"title":"방울토마토","kcal":32},{"title":"바나나","kcal":221},{"title":"삶은계란","kcal":73},{"title":"건강즙(석류)","kcal":50},{"title":"핫바","kcal":80}],"hallFloor":["3"]}},"dinner":{"3AAE5BA":{"title":"닭곰탕","course":"탕맛기픈","totalKcal":1114,"kcal":547,"imgUrl":"https://seoseunghyun.github.io/wsharp/resource/img/pending.jpg","list":[{"title":"닭곰탕","kcal":547},{"title":"흑미밥","kcal":312},{"title":"두부조림","kcal":185},{"title":"미역줄기볶음","kcal":42},{"title":"무생채","kcal":28}],"hallFloor":["3"]},"3ABE5BA":{"title":"소불고기","course":"탕맛기픈","totalKcal":1040,"kcal":421,"imgUrl":"https://seoseunghyun.github.io/wsharp/resource/img/pending.jpg","list":[{"title":"소불고기","kcal":421},{"title":"흑미밥","kcal":312},{"title":"사각어묵국","kcal":52},{"title":"두부조림","kcal":185},{"title":"미역줄기볶음","kcal":42},{"title":"무생채","kcal":28}],"hallFloor":["3"]},"3BBE5BA":{"title":"잔치국수","course":"봄이온소반","totalKcal":634,"kcal":440,"imgUrl":"https://seoseunghyun.github.io/wsharp/resource/img/pending.jpg","list":[{"title":"잔치국수","kcal":440},{"title":"고추튀김&간장","kcal":108},{"title":"열무김치","kcal":31},{"title":"1종과일","kcal":55}],"hallFloor":[]},"3DDE5BA":{"title":"매운순두부라면","course":"SnapSnack","totalKcal":1178,"kcal":697,"imgUrl":"https://seoseunghyun.github.io/wsharp/resource/img/pending.jpg","list":[{"title":"매운순두부라면","kcal":697},{"title":"오징어핫바","kcal":135},{"title":"떡꼬치","kcal":265},{"title":"단무지","kcal":7},{"title":"음료","kcal":74}],"hallFloor":[]},"3BBE5B9":{"title":"매콤삼겹살덮밥","course":"BROWN GRILL","totalKcal":1590,"kcal":1471,"imgUrl":"https://seoseunghyun.github.io/wsharp/resource/img/pending.jpg","list":[{"title":"매콤삼겹살덮밥","kcal":1471},{"title":"유부장국","kcal":69},{"title":"양배추샐러드","kcal":12},{"title":"락교","kcal":38}],"hallFloor":[]},"3DDE5B9":{"title":"매콤삼겹살덮밥","course":"가츠&엔","totalKcal":1590,"kcal":1471,"imgUrl":"https://seoseunghyun.github.io/wsharp/resource/img/pending.jpg","list":[{"title":"매콤삼겹살덮밥","kcal":1471},{"title":"유부장국","kcal":69},{"title":"양배추샐러드","kcal":12},{"title":"락교","kcal":38}],"hallFloor":["3"]},"3GGE5B9":{"title":"국물자작비빔국수","course":"XingFu(China)","totalKcal":1355,"kcal":802,"imgUrl":"https://seoseunghyun.github.io/wsharp/resource/img/pending.jpg","list":[{"title":"국물자작비빔국수","kcal":802},{"title":"오징어핫바","kcal":135},{"title":"떡꼬치","kcal":265},{"title":"열무김치","kcal":29},{"title":"1종과일","kcal":55},{"title":"유부장국","kcal":69}],"hallFloor":["3"]},"3AAE5B7":{"title":"더블에그&햄치아바타","course":"T/O 샌드위치","totalKcal":1278,"kcal":333,"imgUrl":"https://seoseunghyun.github.io/wsharp/resource/img/pending.jpg","list":[{"title":"더블에그&햄치아바타","kcal":333},{"title":"치킨까스버거샌드위치","kcal":575},{"title":"BLT샌드위치","kcal":370}],"hallFloor":["3"]},"3BBE5B7":{"title":"허니듀메론","course":"T/O 과일","totalKcal":2227,"kcal":65,"imgUrl":"https://seoseunghyun.github.io/wsharp/resource/img/pending.jpg","list":[{"title":"허니듀메론","kcal":65},{"title":"용과","kcal":63},{"title":"대추방울토마토","kcal":32},{"title":"완숙계란","kcal":434},{"title":"완숙계란&닭가슴살육포(매콤)","kcal":220},{"title":"고구마","kcal":384},{"title":"감자","kcal":211},{"title":"요거초코통통","kcal":344},{"title":"귀리쉐이크","kcal":172},{"title":"비건그린","kcal":141},{"title":"초코","kcal":161}],"hallFloor":["3"]},"3CCE5B7":{"title":"크랩살에그샐러드","course":"T/O 샐러드","totalKcal":2072,"kcal":455,"imgUrl":"https://seoseunghyun.github.io/wsharp/resource/img/pending.jpg","list":[{"title":"크랩살에그샐러드","kcal":455},{"title":"S라인샐러드","kcal":468},{"title":"비건너비아니두부샌드","kcal":466},{"title":"&[비건토핑]견과류","kcal":90},{"title":"&[오보토핑]메추리알","kcal":50},{"title":"[콤보]½베이컨에그샐러드+½시그니쳐디럭스샌드위치","kcal":543}],"hallFloor":["3"]},"3DDE5B7":{"title":"건강한베리베리브레드","course":"T/O 빵","totalKcal":3717,"kcal":280,"imgUrl":"https://seoseunghyun.github.io/wsharp/resource/img/pending.jpg","list":[{"title":"건강한베리베리브레드","kcal":280},{"title":"카스테라","kcal":388},{"title":"피자바게트","kcal":475},{"title":"월넛크림치즈스틱","kcal":310},{"title":"슈크림소보로","kcal":435},{"title":"완두앙금빵","kcal":250},{"title":"시나몬롤페스츄리빵","kcal":330},{"title":"NEW꿀떡꿀떡","kcal":299},{"title":"빅초코칩머핀","kcal":640},{"title":"포켓샌드땅콩크림빵","kcal":310}],"hallFloor":["3"]},"3FFE5B7":{"title":"삼계죽","course":"T/O 죽","totalKcal":734,"kcal":616,"imgUrl":"https://seoseunghyun.github.io/wsharp/resource/img/pending.jpg","list":[{"title":"삼계죽","kcal":616},{"title":"돼지고기장조림","kcal":83},{"title":"오징어젓갈무침","kcal":35}],"hallFloor":["3"]},"3IIE5B7":{"title":"사과","course":"T/O 빵,샌드위치 17종사이드","totalKcal":2330,"kcal":237,"imgUrl":"https://seoseunghyun.github.io/wsharp/resource/img/pending.jpg","list":[{"title":"사과","kcal":237},{"title":"대추방울토마토","kcal":32},{"title":"바나나","kcal":221},{"title":"콘크림컵스프","kcal":95},{"title":"아몬드푸레이크시리얼","kcal":128},{"title":"마시는고구마죽","kcal":110},{"title":"그릭달지않은요거트","kcal":80},{"title":"요거톡(초코그래놀라)","kcal":169},{"title":"허쉬화이트칩위드아몬드쿠키","kcal":247},{"title":"휠터치소시지","kcal":189},{"title":"첵스초코펀오리지날바","kcal":107},{"title":"넛츠피아나인믹스그릭","kcal":47},{"title":"퀴노아넛츠크런치","kcal":133},{"title":"연양갱","kcal":160},{"title":"발효오디와배","kcal":25},{"title":"쁘띠첼(밀감)","kcal":65},{"title":"카라멜팝콘","kcal":285}],"hallFloor":["3"]},"3KFE5B7":{"title":"광명찾은결명자차","course":"T/O 선택음료","totalKcal":5150,"kcal":0,"imgUrl":"https://seoseunghyun.github.io/wsharp/resource/img/pending.jpg","list":[{"title":"광명찾은결명자차","kcal":0},{"title":"닥터유드링크,초코","kcal":167},{"title":"덴마크드링킹,딸기","kcal":260},{"title":"덴마크드링킹,청포도","kcal":280},{"title":"디카페인아메리카노","kcal":16},{"title":"딸기우유","kcal":230},{"title":"레드스무디페트","kcal":180},{"title":"르블렌자몽히비스커스","kcal":36},{"title":"마시는요구르트,액티비아","kcal":82},{"title":"마시는요구르트,윌","kcal":115},{"title":"멸균흰우유","kcal":125},{"title":"모닝시리얼우유","kcal":185},{"title":"바나나우유","kcal":208},{"title":"백산수","kcal":0},{"title":"베지밀B두유","kcal":120},{"title":"비타민워터,파워씨(용과)","kcal":92},{"title":"산펠레그리노,리모네타","kcal":117},{"title":"산펠레그리노,아란시아타로싸","kcal":132},{"title":"산펠레그리노,폼펠모","kcal":137},{"title":"삼다수","kcal":0},{"title":"소화가잘되는우유","kcal":105},{"title":"씨그램,라임","kcal":0},{"title":"아몬드브리즈,언스위트","kcal":35},{"title":"아몬드브리즈,오리지널","kcal":45},{"title":"아몬드브리즈,프로틴","kcal":65},{"title":"아이시스에코","kcal":0},{"title":"아임보리","kcal":0},{"title":"아침햇살미유","kcal":70},{"title":"알로에베라킹페트","kcal":185},{"title":"야채랑사과","kcal":95},{"title":"약콩두유","kcal":75},{"title":"에비앙","kcal":0},{"title":"옥수수수염차","kcal":0},{"title":"요구르트,그란데","kcal":140},{"title":"이프청포도주스","kcal":150},{"title":"저지방우유","kcal":80},{"title":"칠성사이다","kcal":110},{"title":"코카콜라","kcal":108},{"title":"코카콜라제로","kcal":0},{"title":"코코아우유","kcal":250},{"title":"콜드,오렌지주스","kcal":135},{"title":"콜드,포도주스","kcal":152},{"title":"콜드브루아메리카노","kcal":10},{"title":"토레타캔","kcal":58},{"title":"트레비,레몬","kcal":0},{"title":"트레비,플레인","kcal":0},{"title":"티오피,마스터라떼","kcal":110},{"title":"티즐유자그린티페트","kcal":200},{"title":"파워에이드캔","kcal":36},{"title":"페리에,라임","kcal":0},{"title":"페리에,피치","kcal":0},{"title":"헛개수","kcal":0},{"title":"현미참두유 ","kcal":144},{"title":"흰우유,200ML","kcal":130},{"title":"흰우유,250ML","kcal":180}],"hallFloor":["3"]},"3KGE5B7":{"title":"T/O 상시코너","course":"T/O 상시코너","totalKcal":0,"kcal":0,"imgUrl":"https://seoseunghyun.github.io/wsharp/resource/img/pending.jpg","list":[{"title":"T/O 상시코너","kcal":0}],"hallFloor":["3"]},"3KKE5B7":{"title":"그린데이","course":"T/O 착즙주스1","totalKcal":696,"kcal":155,"imgUrl":"https://seoseunghyun.github.io/wsharp/resource/img/pending.jpg","list":[{"title":"그린데이","kcal":155},{"title":"썬라이즈","kcal":170},{"title":"프레시토마토","kcal":110},{"title":"ABC주스","kcal":115},{"title":"삶은계란","kcal":73},{"title":"견과류","kcal":73}],"hallFloor":["3"]}},"midnight":{}}}