{"restaurant":{"name":"구미1캠","hallList":["구미1캠"]},"menuList":{"morning":{"1AAE201":{"title":"왕계란탕or","course":"정식","totalKcal":1202,"kcal":213,"imgUrl":"https://seoseunghyun.github.io/wsharp/resource/img/pending.jpg","list":[{"title":"왕계란탕or","kcal":213},{"title":"해물탕","kcal":155},{"title":"모둠장조림","kcal":370},{"title":"쥐어채고추장볶음","kcal":144},{"title":"율무밥","kcal":303},{"title":"포기김치","kcal":17}],"hallFloor":["구미1캠"]},"1B1E201":{"title":"코코팝스","course":"T/O 시리얼","totalKcal":175,"kcal":175,"imgUrl":"https://seoseunghyun.github.io/wsharp/resource/img/pending.jpg","list":[{"title":"코코팝스","kcal":175}],"hallFloor":["구미1캠"]},"1E1E201":{"title":"바나나","course":"T/O 과일","totalKcal":298,"kcal":232,"imgUrl":"https://seoseunghyun.github.io/wsharp/resource/img/pending.jpg","list":[{"title":"바나나","kcal":232},{"title":"적포도","kcal":66}],"hallFloor":["구미1캠"]},"1G1E201":{"title":"마블케익빵","course":"T/O 빵","totalKcal":442,"kcal":395,"imgUrl":"https://seoseunghyun.github.io/wsharp/resource/img/pending.jpg","list":[{"title":"마블케익빵","kcal":395},{"title":"견과류","kcal":47}],"hallFloor":["구미1캠"]},"1K1E201":{"title":"햄김치주먹밥","course":"T/O 주먹밥","totalKcal":450,"kcal":437,"imgUrl":"https://seoseunghyun.github.io/wsharp/resource/img/pending.jpg","list":[{"title":"햄김치주먹밥","kcal":437},{"title":"단무지","kcal":3},{"title":"포기김치","kcal":10}],"hallFloor":["구미1캠"]},"1L1E201":{"title":"홍차선식","course":"T/O 선식","totalKcal":427,"kcal":205,"imgUrl":"https://seoseunghyun.github.io/wsharp/resource/img/pending.jpg","list":[{"title":"홍차선식","kcal":205},{"title":"클래식선식","kcal":222}],"hallFloor":["구미1캠"]},"1L2E201":{"title":"코코넛프로틴","course":"T/O 웰프로틴","totalKcal":166,"kcal":166,"imgUrl":"https://seoseunghyun.github.io/wsharp/resource/img/pending.jpg","list":[{"title":"코코넛프로틴","kcal":166}],"hallFloor":["구미1캠"]}},"lunch":{"2AAE201":{"title":"부추된장찌개","course":"정식A","totalKcal":964,"kcal":147,"imgUrl":"https://seoseunghyun.github.io/wsharp/resource/img/pending.jpg","list":[{"title":"부추된장찌개","kcal":147},{"title":"돼지고기목살생강구이","kcal":359},{"title":"깐풍우엉조림","kcal":93},{"title":"율무밥","kcal":348},{"title":"포기김치","kcal":17}],"hallFloor":["구미1캠"]},"2CCE201":{"title":"라면<br /><span style=\"font-size:12px\">(너구리라면)</span>","course":"누들","totalKcal":1127,"kcal":553,"imgUrl":"https://seoseunghyun.github.io/wsharp/resource/img/pending.jpg","list":[{"title":"라면(너구리라면)","kcal":553},{"title":"진미채김밥","kcal":428},{"title":"찹쌀도너츠","kcal":101},{"title":"요쿠르트","kcal":35},{"title":"포기김치","kcal":10}],"hallFloor":["구미1캠"]}},"dinner":{"3BBE201":{"title":"해물순두부찌개","course":"<한상차림>","totalKcal":1316,"kcal":244,"imgUrl":"https://seoseunghyun.github.io/wsharp/resource/img/pending.jpg","list":[{"title":"해물순두부찌개","kcal":244},{"title":"쇠고기숙주볶음","kcal":209},{"title":"낙지채소볶음","kcal":104},{"title":"미트볼케첩조림","kcal":218},{"title":"흑임자깻잎전","kcal":159},{"title":"고들빼기무침","kcal":17},{"title":"율무밥","kcal":348},{"title":"포기김치","kcal":17}],"hallFloor":["구미1캠"]}},"midnight":{"4AAE201":{"title":"부추된장찌개","course":"핫볼","totalKcal":1047,"kcal":147,"imgUrl":"https://seoseunghyun.github.io/wsharp/resource/img/pending.jpg","list":[{"title":"부추된장찌개","kcal":147},{"title":"돼지고기목살생강구이","kcal":359},{"title":"깐풍우엉조림","kcal":93},{"title":"파김치","kcal":83},{"title":"율무밥","kcal":348},{"title":"포기김치","kcal":17}],"hallFloor":["구미1캠"]}}}}