{"restaurant":{"name":"polaris","hallList":["polaris"]},"menuList":{"morning":{"1AAE1C7":{"title":"김치해장국","course":"A","totalKcal":870,"kcal":137,"imgUrl":"https://seoseunghyun.github.io/wsharp/resource/img/pending.jpg","list":[{"title":"김치해장국","kcal":137},{"title":"흑미밥","kcal":312},{"title":"소불고기","kcal":318},{"title":"건새우마늘종볶음","kcal":69},{"title":"톳양파무침","kcal":34}],"hallFloor":["polaris"]},"1BBE1C7":{"title":"아메리칸조식","course":"B","totalKcal":1573,"kcal":0,"imgUrl":"https://seoseunghyun.github.io/wsharp/resource/img/pending.jpg","list":[{"title":"아메리칸조식","kcal":0},{"title":"웰모닝","kcal":167},{"title":"그린샐러드","kcal":9},{"title":"호밀빅식빵","kcal":116},{"title":"감자스프","kcal":79},{"title":"씨리얼","kcal":385},{"title":"음료","kcal":135},{"title":"요거트","kcal":282},{"title":"도이치소시지구이","kcal":171},{"title":"계란후라이","kcal":74},{"title":"구운채소","kcal":72},{"title":"토핑(블랙올리브)","kcal":3},{"title":"토핑(체다치즈)","kcal":24},{"title":"1종과일","kcal":56}],"hallFloor":["polaris"]},"1K1E1C7":{"title":"샌드위치 3종 中 택1","course":"T/O 샌드위치","totalKcal":1179,"kcal":0,"imgUrl":"https://seoseunghyun.github.io/wsharp/resource/img/pending.jpg","list":[{"title":"샌드위치 3종 中 택1","kcal":0},{"title":"튜나클럽","kcal":445},{"title":"모닝쌀머핀바질페스토샌드위치","kcal":300},{"title":"햄치즈","kcal":275},{"title":"2종과일","kcal":159}],"hallFloor":["polaris"]},"1K2E1C7":{"title":"사과","course":"T/O 과일","totalKcal":1998,"kcal":237,"imgUrl":"https://seoseunghyun.github.io/wsharp/resource/img/pending.jpg","list":[{"title":"사과","kcal":237},{"title":"파인애플","kcal":127},{"title":"청포도","kcal":66},{"title":"완숙계란","kcal":434},{"title":"촉촉한계란&오리지널닭가슴살소시지","kcal":264},{"title":"고구마","kcal":384},{"title":"감자","kcal":211},{"title":"요거복숭아","kcal":275}],"hallFloor":["polaris"]},"1K3E1C7":{"title":"샐러드 2종 中 택1","course":"T/O 샐러드","totalKcal":518,"kcal":0,"imgUrl":"https://seoseunghyun.github.io/wsharp/resource/img/pending.jpg","list":[{"title":"샐러드 2종 中 택1","kcal":0},{"title":"연두부견과류샐러드","kcal":211},{"title":"베이컨에그샐러드","kcal":307}],"hallFloor":["polaris"]},"1K6E1C7":{"title":"빵 or 떡 5종 中 택1","course":"T/O 빵","totalKcal":2196,"kcal":0,"imgUrl":"https://seoseunghyun.github.io/wsharp/resource/img/pending.jpg","list":[{"title":"빵 or 떡 5종 中 택1","kcal":0},{"title":"베이컨에그크라상","kcal":341},{"title":"자연치즈순치즈빵","kcal":235},{"title":"굿브레드","kcal":203},{"title":"단팥소보로","kcal":390},{"title":"삼색경단","kcal":585},{"title":"1종과일","kcal":57},{"title":"시리얼&우유","kcal":180},{"title":"두유","kcal":110},{"title":"요거트","kcal":95}],"hallFloor":["polaris"]},"1K7E1C7":{"title":"햄<br /><span style=\"font-size:12px\">(스팸)</span>주먹밥","course":"T/O 주먹밥","totalKcal":1069,"kcal":541,"imgUrl":"https://seoseunghyun.github.io/wsharp/resource/img/pending.jpg","list":[{"title":"햄(스팸)주먹밥","kcal":541},{"title":"파프리카 계란스크램블토핑","kcal":163},{"title":"1종과일","kcal":122},{"title":"절임반찬","kcal":31},{"title":"구운란","kcal":75},{"title":"건강즙","kcal":48},{"title":"핫바","kcal":89}],"hallFloor":["polaris"]},"1K8E1C7":{"title":"명태회김밥","course":"T/O 김밥","totalKcal":1249,"kcal":566,"imgUrl":"https://seoseunghyun.github.io/wsharp/resource/img/pending.jpg","list":[{"title":"명태회김밥","kcal":566},{"title":"½명태회김밥+피자오믈렛","kcal":407},{"title":"1종과일","kcal":58},{"title":"구운란","kcal":75},{"title":"건강즙","kcal":48},{"title":"핫바","kcal":95}],"hallFloor":["polaris"]},"1KCE1C7":{"title":"착즙 4종 中 택1","course":"T/O 착즙주스","totalKcal":916,"kcal":0,"imgUrl":"https://seoseunghyun.github.io/wsharp/resource/img/pending.jpg","list":[{"title":"착즙 4종 中 택1","kcal":0},{"title":"밀싹애플","kcal":155},{"title":"부스트업","kcal":165},{"title":"빌베리&마리골드","kcal":165},{"title":"블랙&비타D","kcal":265},{"title":"삶은계란","kcal":83},{"title":"견과류","kcal":83}],"hallFloor":["polaris"]},"1KEE1C7":{"title":"선식 3종 中 택1","course":"T/O 선식","totalKcal":1180,"kcal":0,"imgUrl":"https://seoseunghyun.github.io/wsharp/resource/img/pending.jpg","list":[{"title":"선식 3종 中 택1","kcal":0},{"title":"단호박","kcal":176},{"title":"플레인라이트","kcal":206},{"title":"녹차","kcal":158},{"title":"우유","kcal":180},{"title":"두유","kcal":110},{"title":"삶은계란","kcal":83},{"title":"견과류","kcal":83},{"title":"2종과일","kcal":184}],"hallFloor":["polaris"]}},"lunch":{"2AAE1C7":{"title":"전복미역탕","course":"A","totalKcal":1031,"kcal":98,"imgUrl":"https://seoseunghyun.github.io/wsharp/resource/img/pending.jpg","list":[{"title":"전복미역탕","kcal":98},{"title":"쌀밥","kcal":449},{"title":"떡갈비조림","kcal":345},{"title":"계란찜","kcal":88},{"title":"양파장아찌","kcal":51}],"hallFloor":["polaris"]},"2BBE1C7":{"title":"제주식고사리삼겹살구이","course":"B","totalKcal":1401,"kcal":879,"imgUrl":"https://seoseunghyun.github.io/wsharp/resource/img/pending.jpg","list":[{"title":"제주식고사리삼겹살구이","kcal":879},{"title":"흑미밥","kcal":312},{"title":"두부된장국","kcal":59},{"title":"쌈무","kcal":32},{"title":"고추냉이","kcal":65},{"title":"쌈장","kcal":54}],"hallFloor":["polaris"]},"2CCE1C7":{"title":"우삼겹간장비빔국수","course":"C","totalKcal":1257,"kcal":671,"imgUrl":"https://seoseunghyun.github.io/wsharp/resource/img/pending.jpg","list":[{"title":"우삼겹간장비빔국수","kcal":671},{"title":"1종과일","kcal":165},{"title":"단호박부꾸미","kcal":286},{"title":"무말랭이무침","kcal":66},{"title":"유부장국","kcal":69}],"hallFloor":["polaris"]},"2RRE1C7":{"title":"수제등심돈가스","course":"T/O 도시락","totalKcal":2097,"kcal":872,"imgUrl":"https://seoseunghyun.github.io/wsharp/resource/img/pending.jpg","list":[{"title":"수제등심돈가스","kcal":872},{"title":"우동","kcal":534},{"title":"새우튀김","kcal":125},{"title":"단호박샐러드","kcal":152},{"title":"생수","kcal":0},{"title":"왕교자만두튀김","kcal":94},{"title":"락교","kcal":31},{"title":"후리가케양념밥","kcal":209},{"title":"초생강절임","kcal":6},{"title":"돈가스소스","kcal":74}],"hallFloor":["polaris"]},"2HHE1C7":{"title":"S라인샐러드","course":"T/O 샐러드","totalKcal":673,"kcal":468,"imgUrl":"https://seoseunghyun.github.io/wsharp/resource/img/pending.jpg","list":[{"title":"S라인샐러드","kcal":468},{"title":"요거밀(단호박)","kcal":205}],"hallFloor":["polaris"]},"2K2E1C7":{"title":"파인애플","course":"T/O 과일","totalKcal":1946,"kcal":127,"imgUrl":"https://seoseunghyun.github.io/wsharp/resource/img/pending.jpg","list":[{"title":"파인애플","kcal":127},{"title":"레드키위","kcal":108},{"title":"거봉","kcal":122},{"title":"완숙계란","kcal":434},{"title":"촉촉한계란&뉴트리션바(베리)","kcal":355},{"title":"고구마","kcal":384},{"title":"감자","kcal":211},{"title":"요거밀(단호박)","kcal":205}],"hallFloor":["polaris"]},"2K6E1C7":{"title":"빵 4종 中 택2","course":"T/O 빵","totalKcal":1824,"kcal":0,"imgUrl":"https://seoseunghyun.github.io/wsharp/resource/img/pending.jpg","list":[{"title":"빵 4종 中 택2","kcal":0},{"title":"자연치즈순치즈빵","kcal":235},{"title":"고메버터식빵","kcal":485},{"title":"구름크림빵","kcal":230},{"title":"순수우유후레쉬번","kcal":580},{"title":"2종과일","kcal":89},{"title":"요거밀(단호박)","kcal":205}],"hallFloor":["polaris"]},"2K8E1C7":{"title":"소불고기김밥","course":"T/O 김밥","totalKcal":1430,"kcal":549,"imgUrl":"https://seoseunghyun.github.io/wsharp/resource/img/pending.jpg","list":[{"title":"소불고기김밥","kcal":549},{"title":"½소불고기김밥+유부초밥","kcal":436},{"title":"1종과일","kcal":32},{"title":"구운란","kcal":75},{"title":"건강즙","kcal":35},{"title":"핫바","kcal":98},{"title":"요거밀(단호박)","kcal":205}],"hallFloor":["polaris"]},"2KCE1C7":{"title":"착즙 2종 中 택1","course":"T/O 착즙주스","totalKcal":691,"kcal":0,"imgUrl":"https://seoseunghyun.github.io/wsharp/resource/img/pending.jpg","list":[{"title":"착즙 2종 中 택1","kcal":0},{"title":"밀싹애플","kcal":155},{"title":"빌베리&마리골드","kcal":165},{"title":"삶은계란","kcal":83},{"title":"견과류","kcal":83},{"title":"요거밀(단호박)","kcal":205}],"hallFloor":["polaris"]},"2KEE1C7":{"title":"선식 3종 中 택1","course":"T/O 선식","totalKcal":1290,"kcal":0,"imgUrl":"https://seoseunghyun.github.io/wsharp/resource/img/pending.jpg","list":[{"title":"선식 3종 中 택1","kcal":0},{"title":"단호박","kcal":176},{"title":"플레인라이트","kcal":206},{"title":"녹차","kcal":158},{"title":"우유","kcal":180},{"title":"두유","kcal":110},{"title":"삶은계란","kcal":83},{"title":"견과류","kcal":83},{"title":"2종과일","kcal":89},{"title":"요거밀(단호박)","kcal":205}],"hallFloor":["polaris"]},"2MME1C7":{"title":"잡채","course":"추가찬","totalKcal":310,"kcal":310,"imgUrl":"https://seoseunghyun.github.io/wsharp/resource/img/pending.jpg","list":[{"title":"잡채","kcal":310}],"hallFloor":["polaris"]}},"dinner":{"3AAE1C7":{"title":"황태해장국","course":"A","totalKcal":869,"kcal":232,"imgUrl":"https://seoseunghyun.github.io/wsharp/resource/img/pending.jpg","list":[{"title":"황태해장국","kcal":232},{"title":"흑미밥","kcal":312},{"title":"햄(로스팜)계란전","kcal":250},{"title":"도토리묵무침","kcal":48},{"title":"오이지무침","kcal":27}],"hallFloor":["polaris"]},"3BBE1C7":{"title":"닭개장","course":"B","totalKcal":883,"kcal":246,"imgUrl":"https://seoseunghyun.github.io/wsharp/resource/img/pending.jpg","list":[{"title":"닭개장","kcal":246},{"title":"흑미밥","kcal":312},{"title":"햄(로스팜)계란전","kcal":250},{"title":"도토리묵무침","kcal":48},{"title":"오이지무침","kcal":27}],"hallFloor":["polaris"]},"3CCE1C7":{"title":"라면<br /><span style=\"font-size:12px\">(참깨라면)</span>","course":"C","totalKcal":837,"kcal":459,"imgUrl":"https://seoseunghyun.github.io/wsharp/resource/img/pending.jpg","list":[{"title":"라면(참깨라면)","kcal":459},{"title":"순대볶음","kcal":228},{"title":"포기김치","kcal":24},{"title":"단무지","kcal":5},{"title":"후식1종","kcal":121}],"hallFloor":["polaris"]},"3HHE1C7":{"title":"연어포케샐러드","course":"T/O 샐러드","totalKcal":597,"kcal":597,"imgUrl":"https://seoseunghyun.github.io/wsharp/resource/img/pending.jpg","list":[{"title":"연어포케샐러드","kcal":597}],"hallFloor":["polaris"]},"3K1E1C7":{"title":"햄&코울슬로샌드위치","course":"T/O 샌드위치","totalKcal":1543,"kcal":460,"imgUrl":"https://seoseunghyun.github.io/wsharp/resource/img/pending.jpg","list":[{"title":"햄&코울슬로샌드위치","kcal":460},{"title":"로제치킨샌드위치","kcal":385},{"title":"BLT샌드위치","kcal":385},{"title":"믹스과일","kcal":234},{"title":"미니샐러드","kcal":79}],"hallFloor":["polaris"]},"3K2E1C7":{"title":"단감","course":"T/O 과일","totalKcal":2181,"kcal":176,"imgUrl":"https://seoseunghyun.github.io/wsharp/resource/img/pending.jpg","list":[{"title":"단감","kcal":176},{"title":"트윈핑거바나나","kcal":221},{"title":"거봉","kcal":122},{"title":"완숙계란","kcal":434},{"title":"촉촉한계란&뉴트리션바(베리)","kcal":355},{"title":"고구마","kcal":384},{"title":"감자","kcal":211},{"title":"요거베리","kcal":278}],"hallFloor":["polaris"]},"3K6E1C7":{"title":"고메버터식빵","course":"T/O 빵","totalKcal":2577,"kcal":485,"imgUrl":"https://seoseunghyun.github.io/wsharp/resource/img/pending.jpg","list":[{"title":"고메버터식빵","kcal":485},{"title":"미니깨찰빵","kcal":360},{"title":"한입쏙크림치즈파이","kcal":390},{"title":"꼬마카스테라","kcal":420},{"title":"꼬마꿀호떡빵","kcal":366},{"title":"조각롤케이크빵","kcal":243},{"title":"믹스과일","kcal":234},{"title":"미니샐러드","kcal":79}],"hallFloor":["polaris"]},"3KBE1C7":{"title":"참치누룽지죽","course":"T/O 죽","totalKcal":893,"kcal":604,"imgUrl":"https://seoseunghyun.github.io/wsharp/resource/img/pending.jpg","list":[{"title":"참치누룽지죽","kcal":604},{"title":"쇠고기장조림","kcal":254},{"title":"오징어젓갈무침","kcal":35}],"hallFloor":["polaris"]},"3KCE1C7":{"title":"밀싹애플","course":"T/O 착즙주스","totalKcal":486,"kcal":155,"imgUrl":"https://seoseunghyun.github.io/wsharp/resource/img/pending.jpg","list":[{"title":"밀싹애플","kcal":155},{"title":"빌베리&마리골드","kcal":165},{"title":"삶은계란","kcal":83},{"title":"견과류","kcal":83}],"hallFloor":["polaris"]},"3KEE1C7":{"title":"단호박","course":"T/O 선식","totalKcal":1119,"kcal":176,"imgUrl":"https://seoseunghyun.github.io/wsharp/resource/img/pending.jpg","list":[{"title":"단호박","kcal":176},{"title":"플레인라이트","kcal":206},{"title":"녹차","kcal":158},{"title":"우유","kcal":180},{"title":"두유","kcal":110},{"title":"삶은계란","kcal":83},{"title":"견과류","kcal":83},{"title":"2종과일","kcal":123}],"hallFloor":["polaris"]}},"midnight":{}}}