{"restaurant":{"name":"family","hallList":["family"]},"menuList":{"morning":{"1A1E1HQ":{"title":"돼지고기고추장찌개","course":"A","totalKcal":945,"kcal":357,"imgUrl":"https://seoseunghyun.github.io/wsharp/resource/img/pending.jpg","list":[{"title":"돼지고기고추장찌개","kcal":357},{"title":"흑미밥","kcal":312},{"title":"동태전","kcal":164},{"title":"얼갈이나물","kcal":20},{"title":"브로콜리&다시마숙회","kcal":92}],"hallFloor":["family"]},"1B1E1HQ":{"title":"오징어미나리찜","course":"B","totalKcal":823,"kcal":227,"imgUrl":"https://seoseunghyun.github.io/wsharp/resource/img/pending.jpg","list":[{"title":"오징어미나리찜","kcal":227},{"title":"흑미밥","kcal":312},{"title":"무들깻국","kcal":34},{"title":"즉석계란후라이","kcal":123},{"title":"유채나물","kcal":27},{"title":"브로콜리,다시마숙회&초장","kcal":100}],"hallFloor":["family"]},"1C2E1HQ":{"title":"★아메리칸조식★","course":"아메리칸조식","totalKcal":1433,"kcal":0,"imgUrl":"https://seoseunghyun.github.io/wsharp/resource/img/pending.jpg","list":[{"title":"★아메리칸조식★","kcal":0},{"title":"디아볼로피자토스트","kcal":498},{"title":"크로와상","kcal":247},{"title":"완두콩스프","kcal":58},{"title":"시리얼","kcal":154},{"title":"요거트","kcal":93},{"title":"으깬샐러드","kcal":116},{"title":"오믈렛","kcal":111},{"title":"그린샐러드","kcal":8},{"title":"1종과일","kcal":52},{"title":"음료","kcal":96}],"hallFloor":["family"]},"1K1E1HR":{"title":"샌드위치 3종 中 택1","course":"T/O 샌드위치","totalKcal":1253,"kcal":0,"imgUrl":"https://seoseunghyun.github.io/wsharp/resource/img/pending.jpg","list":[{"title":"샌드위치 3종 中 택1","kcal":0},{"title":"튜나클럽","kcal":445},{"title":"모닝쌀머핀바질페스토샌드위치","kcal":300},{"title":"햄치즈","kcal":275},{"title":"2종과일","kcal":233}],"hallFloor":["family"]},"1K2E1HR":{"title":"컵푸드 8종 中 택2","course":"T/O 과일","totalKcal":1944,"kcal":0,"imgUrl":"https://seoseunghyun.github.io/wsharp/resource/img/pending.jpg","list":[{"title":"컵푸드 8종 中 택2","kcal":0},{"title":"골드키위","kcal":108},{"title":"사과","kcal":237},{"title":"레드향","kcal":72},{"title":"완숙계란","kcal":434},{"title":"촉촉한계란&블랙넛츠","kcal":220},{"title":"고구마","kcal":384},{"title":"감자","kcal":211},{"title":"요거베리","kcal":278}],"hallFloor":["family"]},"1K3E1HR":{"title":"샐러드 2종 中 택1","course":"T/O 샐러드","totalKcal":374,"kcal":0,"imgUrl":"https://seoseunghyun.github.io/wsharp/resource/img/pending.jpg","list":[{"title":"샐러드 2종 中 택1","kcal":0},{"title":"카프레제샐러드","kcal":199},{"title":"닭가슴살샐러드","kcal":175}],"hallFloor":["family"]},"1K6E1HR":{"title":"빵 or 떡 5종 中 택1","course":"T/O 빵","totalKcal":2685,"kcal":0,"imgUrl":"https://seoseunghyun.github.io/wsharp/resource/img/pending.jpg","list":[{"title":"빵 or 떡 5종 中 택1","kcal":0},{"title":"밤식빵","kcal":690},{"title":"스크램블에그브리오쉬","kcal":285},{"title":"소시지패스트리","kcal":345},{"title":"흑당크림소보로","kcal":335},{"title":"삼색경단","kcal":585},{"title":"1종과일","kcal":170},{"title":"시리얼&우유","kcal":180},{"title":"요거트","kcal":95}],"hallFloor":["family"]},"1K7E1HR":{"title":"멸치아몬드주먹밥","course":"T/O 주먹밥","totalKcal":897,"kcal":460,"imgUrl":"https://seoseunghyun.github.io/wsharp/resource/img/pending.jpg","list":[{"title":"멸치아몬드주먹밥","kcal":460},{"title":"햄 계란스크램블토핑","kcal":181},{"title":"1종과일","kcal":58},{"title":"절임반찬","kcal":20},{"title":"구운란","kcal":75},{"title":"건강즙","kcal":28},{"title":"핫바","kcal":75}],"hallFloor":["family"]},"1K8E1HR":{"title":"묵은지치즈김밥","course":"T/O 김밥","totalKcal":1363,"kcal":665,"imgUrl":"https://seoseunghyun.github.io/wsharp/resource/img/pending.jpg","list":[{"title":"묵은지치즈김밥","kcal":665},{"title":"½묵은지치즈김밥+유부초밥","kcal":465},{"title":"1종과일","kcal":58},{"title":"구운란","kcal":75},{"title":"건강즙","kcal":25},{"title":"핫바","kcal":75}],"hallFloor":["family"]},"1KCE1HR":{"title":"착즙 4종 中 택1","course":"T/O 착즙주스","totalKcal":752,"kcal":0,"imgUrl":"https://seoseunghyun.github.io/wsharp/resource/img/pending.jpg","list":[{"title":"착즙 4종 中 택1","kcal":0},{"title":"패션프루츠","kcal":165},{"title":"토마토주스","kcal":151},{"title":"썬라이즈","kcal":170},{"title":"그린리프","kcal":120},{"title":"삶은계란","kcal":73},{"title":"견과류","kcal":73}],"hallFloor":["family"]},"1KEE1HR":{"title":"선식 3종 中 택1","course":"T/O 선식","totalKcal":1209,"kcal":0,"imgUrl":"https://seoseunghyun.github.io/wsharp/resource/img/pending.jpg","list":[{"title":"선식 3종 中 택1","kcal":0},{"title":"단호박","kcal":176},{"title":"플레인라이트","kcal":206},{"title":"녹차","kcal":158},{"title":"우유","kcal":180},{"title":"두유","kcal":110},{"title":"삶은계란","kcal":73},{"title":"견과류","kcal":73},{"title":"2종과일","kcal":233}],"hallFloor":["family"]}},"lunch":{"2A1E1HQ":{"title":"육개장","course":"A","totalKcal":1139,"kcal":401,"imgUrl":"https://seoseunghyun.github.io/wsharp/resource/img/pending.jpg","list":[{"title":"육개장","kcal":401},{"title":"흑미밥","kcal":312},{"title":"너비아니파프리카볶음","kcal":263},{"title":"가지나물","kcal":29},{"title":"상추겉절이","kcal":134}],"hallFloor":["family"]},"2B1E1HQ":{"title":"참치채소비빔밥","course":"B","totalKcal":1231,"kcal":687,"imgUrl":"https://seoseunghyun.github.io/wsharp/resource/img/pending.jpg","list":[{"title":"참치채소비빔밥","kcal":687},{"title":"유부장국","kcal":82},{"title":"너비아니파프리카볶음","kcal":217},{"title":"마카로니콘샐러드","kcal":205},{"title":"오이지무침","kcal":40}],"hallFloor":["family"]},"2C1E1HQ":{"title":"뽀모도로파스타","course":"C","totalKcal":977,"kcal":671,"imgUrl":"https://seoseunghyun.github.io/wsharp/resource/img/pending.jpg","list":[{"title":"뽀모도로파스타","kcal":671},{"title":"가니쉬빵","kcal":155},{"title":"그린샐러드","kcal":8},{"title":"피클","kcal":26},{"title":"할라피뇨","kcal":17},{"title":"음료","kcal":100}],"hallFloor":["family"]},"2DXE1HQ":{"title":"매운삼겹살자장면","course":"선택식","totalKcal":1529,"kcal":1282,"imgUrl":"https://seoseunghyun.github.io/wsharp/resource/img/pending.jpg","list":[{"title":"매운삼겹살자장면","kcal":1282},{"title":"지마구","kcal":182},{"title":"게맛살냉채","kcal":55},{"title":"단무지","kcal":10}],"hallFloor":["family"]},"2E1E1HQ":{"title":"밀푀유나베","course":"전골","totalKcal":414,"kcal":414,"imgUrl":"https://seoseunghyun.github.io/wsharp/resource/img/pending.jpg","list":[{"title":"밀푀유나베","kcal":414}],"hallFloor":["family"]},"2MME1HQ":{"title":"고등어무조림","course":"추가찬","totalKcal":262,"kcal":262,"imgUrl":"https://seoseunghyun.github.io/wsharp/resource/img/pending.jpg","list":[{"title":"고등어무조림","kcal":262}],"hallFloor":["family"]},"2F1E1HQ":{"title":"불닭볶음라면","course":"SnapSnack","totalKcal":1188,"kcal":645,"imgUrl":"https://seoseunghyun.github.io/wsharp/resource/img/pending.jpg","list":[{"title":"불닭볶음라면","kcal":645},{"title":"게맛살브로콜리주먹밥","kcal":457},{"title":"푸딩","kcal":43},{"title":"단무지","kcal":5},{"title":"포기김치","kcal":38}],"hallFloor":["family"]},"2K2E1HR":{"title":"컵푸드 7종 中 택2","course":"T/O 과일","totalKcal":1722,"kcal":0,"imgUrl":"https://seoseunghyun.github.io/wsharp/resource/img/pending.jpg","list":[{"title":"컵푸드 7종 中 택2","kcal":0},{"title":"단감","kcal":176},{"title":"트윈핑거바나나","kcal":221},{"title":"대추방울토마토","kcal":32},{"title":"완숙계란","kcal":434},{"title":"촉촉한계란&매콤닭가슴살소시지","kcal":264},{"title":"고구마","kcal":384},{"title":"감자","kcal":211}],"hallFloor":["family"]},"2K3E1HR":{"title":"샐러드 2종 中 택1","course":"T/O 샐러드","totalKcal":650,"kcal":0,"imgUrl":"https://seoseunghyun.github.io/wsharp/resource/img/pending.jpg","list":[{"title":"샐러드 2종 中 택1","kcal":0},{"title":"5-메가팩","kcal":261},{"title":"케이준치킨샐러드","kcal":389}],"hallFloor":["family"]},"2K9E1HR":{"title":"도시락컵밥","course":"T/O 컵밥","totalKcal":963,"kcal":907,"imgUrl":"https://seoseunghyun.github.io/wsharp/resource/img/pending.jpg","list":[{"title":"도시락컵밥","kcal":907},{"title":"1종과일","kcal":56}],"hallFloor":["family"]},"2KCE1HR":{"title":"착즙 2종 中 택1","course":"T/O 착즙주스","totalKcal":471,"kcal":0,"imgUrl":"https://seoseunghyun.github.io/wsharp/resource/img/pending.jpg","list":[{"title":"착즙 2종 中 택1","kcal":0},{"title":"그린데이","kcal":155},{"title":"오션블루","kcal":170},{"title":"삶은계란","kcal":73},{"title":"견과류","kcal":73}],"hallFloor":["family"]},"2KEE1HR":{"title":"선식 3종 中 택1","course":"T/O 선식","totalKcal":1189,"kcal":0,"imgUrl":"https://seoseunghyun.github.io/wsharp/resource/img/pending.jpg","list":[{"title":"선식 3종 中 택1","kcal":0},{"title":"말차콜라겐","kcal":200},{"title":"플레인라이트","kcal":206},{"title":"초코","kcal":161},{"title":"우유","kcal":180},{"title":"두유","kcal":110},{"title":"삶은계란","kcal":73},{"title":"견과류","kcal":73},{"title":"2종과일","kcal":186}],"hallFloor":["family"]}},"dinner":{"3A1E1HQ":{"title":"뚝배기불고기","course":"A","totalKcal":847,"kcal":368,"imgUrl":"https://seoseunghyun.github.io/wsharp/resource/img/pending.jpg","list":[{"title":"뚝배기불고기","kcal":368},{"title":"흑미밥","kcal":312},{"title":"매운사각어묵볶음","kcal":77},{"title":"도토리묵&양념장","kcal":56},{"title":"미역초무침","kcal":34}],"hallFloor":["family"]},"3B1E1HQ":{"title":"철판오징어볶음덮밥","course":"B","totalKcal":955,"kcal":630,"imgUrl":"https://seoseunghyun.github.io/wsharp/resource/img/pending.jpg","list":[{"title":"철판오징어볶음덮밥","kcal":630},{"title":"미역국","kcal":23},{"title":"계란가스&칠리소스","kcal":166},{"title":"감자사과샐러드","kcal":120},{"title":"꼬들단무지","kcal":16}],"hallFloor":["family"]},"3DXE1HQ":{"title":"양송이크림함박스테이크","course":"선택식","totalKcal":1181,"kcal":970,"imgUrl":"https://seoseunghyun.github.io/wsharp/resource/img/pending.jpg","list":[{"title":"양송이크림함박스테이크","kcal":970},{"title":"구운야채","kcal":22},{"title":"쌀밥","kcal":42},{"title":"그린샐러드","kcal":8},{"title":"피클","kcal":26},{"title":"할라피뇨","kcal":17},{"title":"브로콜리스프","kcal":96}],"hallFloor":["family"]},"3F1E1HQ":{"title":"부대찌개라면","course":"SnapSnack","totalKcal":1335,"kcal":555,"imgUrl":"https://seoseunghyun.github.io/wsharp/resource/img/pending.jpg","list":[{"title":"부대찌개라면","kcal":555},{"title":"추억의도시락","kcal":618},{"title":"1종과일","kcal":83},{"title":"단무지","kcal":5},{"title":"포기김치","kcal":74}],"hallFloor":["family"]},"3K1E1HR":{"title":"샌드위치 3종 中 택1","course":"T/O 샌드위치","totalKcal":1638,"kcal":0,"imgUrl":"https://seoseunghyun.github.io/wsharp/resource/img/pending.jpg","list":[{"title":"샌드위치 3종 中 택1","kcal":0},{"title":"햄&코울슬로샌드위치","kcal":465},{"title":"로제치킨샌드위치","kcal":385},{"title":"크리미머쉬룸샌드위치","kcal":543},{"title":"믹스과일","kcal":179},{"title":"미니샐러드","kcal":66}],"hallFloor":["family"]},"3K2E1HR":{"title":"컵푸드 8종 中 택2","course":"T/O 과일","totalKcal":2086,"kcal":0,"imgUrl":"https://seoseunghyun.github.io/wsharp/resource/img/pending.jpg","list":[{"title":"컵푸드 8종 中 택2","kcal":0},{"title":"감귤","kcal":170},{"title":"배","kcal":173},{"title":"파인애플","kcal":127},{"title":"완숙계란","kcal":434},{"title":"촉촉한계란&어네스트바(무화과)","kcal":305},{"title":"고구마","kcal":384},{"title":"감자","kcal":211},{"title":"요거복숭아","kcal":282}],"hallFloor":["family"]},"3K3E1HR":{"title":"샐러드 2종 中 택1","course":"T/O 샐러드","totalKcal":762,"kcal":0,"imgUrl":"https://seoseunghyun.github.io/wsharp/resource/img/pending.jpg","list":[{"title":"샐러드 2종 中 택1","kcal":0},{"title":"퀴노아샐러드","kcal":267},{"title":"식스펙샐러드","kcal":495}],"hallFloor":["family"]},"3K6E1HR":{"title":"빵 6종 中 택2","course":"T/O 빵","totalKcal":2333,"kcal":0,"imgUrl":"https://seoseunghyun.github.io/wsharp/resource/img/pending.jpg","list":[{"title":"빵 6종 中 택2","kcal":0},{"title":"고메버터식빵","kcal":485},{"title":"우리쌀슈크림빵","kcal":200},{"title":"미니깨찰빵","kcal":360},{"title":"꼬마카스테라","kcal":430},{"title":"한입가득꿀호떡빵","kcal":370},{"title":"조각롤케이크빵","kcal":243},{"title":"믹스과일","kcal":179},{"title":"미니샐러드","kcal":66}],"hallFloor":["family"]},"3KBE1HR":{"title":"새알심단호박죽","course":"T/O 죽","totalKcal":710,"kcal":476,"imgUrl":"https://seoseunghyun.github.io/wsharp/resource/img/pending.jpg","list":[{"title":"새알심단호박죽","kcal":476},{"title":"쇠고기장조림","kcal":191},{"title":"오징어젓갈무침","kcal":43}],"hallFloor":["family"]},"3KCE1HR":{"title":"착즙 2종 中 택1","course":"T/O 착즙주스","totalKcal":526,"kcal":0,"imgUrl":"https://seoseunghyun.github.io/wsharp/resource/img/pending.jpg","list":[{"title":"착즙 2종 中 택1","kcal":0},{"title":"텐더그린","kcal":205},{"title":"망고애플","kcal":175},{"title":"삶은계란","kcal":73},{"title":"견과류","kcal":73}],"hallFloor":["family"]},"3KEE1HR":{"title":"선식 3종 中 택1","course":"T/O 선식","totalKcal":1252,"kcal":0,"imgUrl":"https://seoseunghyun.github.io/wsharp/resource/img/pending.jpg","list":[{"title":"선식 3종 中 택1","kcal":0},{"title":"바나나","kcal":207},{"title":"플레인라이트","kcal":206},{"title":"코코넛","kcal":166},{"title":"우유","kcal":180},{"title":"두유","kcal":110},{"title":"삶은계란","kcal":73},{"title":"견과류","kcal":73},{"title":"2종과일","kcal":237}],"hallFloor":["family"]}},"midnight":{}}}